{"DocId": 15960, "Sentences": [{"SentenceId": "1", "SentenceText": "Heineken de piyasay\u0131 tatmin edemedi .", "Tokens": [{"Token": "Heineken", "EventTrigger": "O", "EventArgument": "O"}, {"Token": "de", "EventTrigger": "O", "EventArgument": "O"}, {"Token": "piyasay\u0131", "EventTrigger": "O", "EventArgument": "O"}, {"Token": "tatmin", "EventTrigger": "O", "EventArgument": "O"}, {"Token": "edemedi", "EventTrigger": "O", "EventArgument": "O"}, {"Token": ".", "EventTrigger": "O", "EventArgument": "O"}]}, {"SentenceId": "2", "SentenceText": "Bira \u00fcreticisi Heineken , \u00fc\u00e7\u00fcnc\u00fc \u00e7eyrekte y\u0131ll\u0131k bazda y\u00fczde 10 kar art\u0131\u015f\u0131 a\u00e7\u0131klad\u0131 .", "Tokens": [{"Token": "Bira", "EventTrigger": "O", "EventArgument": "B-\u00dcR\u00dcN"}, {"Token": "\u00fcreticisi", "EventTrigger": "\u00dcr\u00fcn-\u0130malat", "EventArgument": "O"}, {"Token": "Heineken", "EventTrigger": "O", "EventArgument": "B-\u015e\u0130RKET"}, {"Token": ",", "EventTrigger": "O", "EventArgument": "O"}, {"Token": "\u00fc\u00e7\u00fcnc\u00fc", "EventTrigger": "O", "EventArgument": "B-ZAMAN"}, {"Token": "\u00e7eyrekte", "EventTrigger": "O", "EventArgument": "I-ZAMAN"}, {"Token": "y\u0131ll\u0131k", "EventTrigger": "O", "EventArgument": "I-ZAMAN"}, {"Token": "bazda", "EventTrigger": "O", "EventArgument": "O"}, {"Token": "y\u00fczde", "EventTrigger": "O", "EventArgument": "B-ORAN"}, {"Token": "10", "EventTrigger": "O", "EventArgument": "I-ORAN"}, {"Token": "kar", "EventTrigger": "Kar-Art\u0131\u015f", "EventArgument": "O"}, {"Token": "art\u0131\u015f\u0131", "EventTrigger": "Kar-Art\u0131\u015f", "EventArgument": "O"}, {"Token": "a\u00e7\u0131klad\u0131", "EventTrigger": "O", "EventArgument": "O"}, {"Token": ".", "EventTrigger": "O", "EventArgument": "O"}]}, {"SentenceId": "3", "SentenceText": "BORSAGUNDEM.COM D\u00fcnyan\u0131n \u00fc\u00e7\u00fcnc\u00fc b\u00fcy\u00fck bira \u00fcreticisi Heineken , \u00fc\u00e7\u00fcnc\u00fc \u00e7eyrekte y\u0131ll\u0131k bazday\u00fczde 10 kar art\u0131\u015f\u0131 a\u00e7\u0131klad\u0131 .", "Tokens": [{"Token": "BORSAGUNDEM.COM", "EventTrigger": "O", "EventArgument": "O"}, {"Token": "D\u00fcnyan\u0131n", "EventTrigger": "O", "EventArgument": "O"}, {"Token": "\u00fc\u00e7\u00fcnc\u00fc", "EventTrigger": "O", "EventArgument": "O"}, {"Token": "b\u00fcy\u00fck", "EventTrigger": "O", "EventArgument": "O"}, {"Token": "bira", "EventTrigger": "O", "EventArgument": "B-\u00dcR\u00dcN"}, {"Token": "\u00fcreticisi", "EventTrigger": "\u00dcr\u00fcn-\u0130malat", "EventArgument": "O"}, {"Token": "Heineken", "EventTrigger": "O", "EventArgument": "B-\u015e\u0130RKET"}, {"Token": ",", "EventTrigger": "O", "EventArgument": "O"}, {"Token": "\u00fc\u00e7\u00fcnc\u00fc", "EventTrigger": "O", "EventArgument": "B-ZAMAN"}, {"Token": "\u00e7eyrekte", "EventTrigger": "O", "EventArgument": "I-ZAMAN"}, {"Token": "y\u0131ll\u0131k", "EventTrigger": "O", "EventArgument": "I-ZAMAN"}, {"Token": "bazday\u00fczde", "EventTrigger": "O", "EventArgument": "O"}, {"Token": "10", "EventTrigger": "O", "EventArgument": "I-ORAN"}, {"Token": "kar", "EventTrigger": "Kar-Art\u0131\u015f", "EventArgument": "O"}, {"Token": "art\u0131\u015f\u0131", "EventTrigger": "Kar-Art\u0131\u015f", "EventArgument": "O"}, {"Token": "a\u00e7\u0131klad\u0131", "EventTrigger": "O", "EventArgument": "O"}, {"Token": ".", "EventTrigger": "O", "EventArgument": "O"}]}, {"SentenceId": "4", "SentenceText": "Hollandal\u0131 \u015firketin \u00e7eyrekteki net kar\u0131 577milyon euro olarak ger\u00e7ekle\u015fti .", "Tokens": [{"Token": "Hollandal\u0131", "EventTrigger": "O", "EventArgument": "O"}, {"Token": "\u015firketin", "EventTrigger": "O", "EventArgument": "O"}, {"Token": "\u00e7eyrekteki", "EventTrigger": "O", "EventArgument": "B-ZAMAN"}, {"Token": "net", "EventTrigger": "O", "EventArgument": "O"}, {"Token": "kar\u0131", "EventTrigger": "Kar-Duyuru", "EventArgument": "O"}, {"Token": "577milyon", "EventTrigger": "O", "EventArgument": "B-PARA"}, {"Token": "euro", "EventTrigger": "O", "EventArgument": "I-PARA"}, {"Token": "olarak", "EventTrigger": "O", "EventArgument": "O"}, {"Token": "ger\u00e7ekle\u015fti", "EventTrigger": "O", "EventArgument": "O"}, {"Token": ".", "EventTrigger": "O", "EventArgument": "O"}]}, {"SentenceId": "5", "SentenceText": "\u00dc\u00e7\u00fcnc\u00fc \u00e7eyrek cirosu , ge\u00e7en y\u0131l\u0131n ayn\u0131 d\u00f6nemine oranla y\u00fczde 7.1 artarak4.97 milyar euro oldu .", "Tokens": [{"Token": "\u00dc\u00e7\u00fcnc\u00fc", "EventTrigger": "O", "EventArgument": "B-ZAMAN"}, {"Token": "\u00e7eyrek", "EventTrigger": "O", "EventArgument": "I-ZAMAN"}, {"Token": "cirosu", "EventTrigger": "Gelir-Art\u0131\u015f", "EventArgument": "O"}, {"Token": ",", "EventTrigger": "O", "EventArgument": "O"}, {"Token": "ge\u00e7en", "EventTrigger": "O", "EventArgument": "B-ZAMAN"}, {"Token": "y\u0131l\u0131n", "EventTrigger": "O", "EventArgument": "I-ZAMAN"}, {"Token": "ayn\u0131", "EventTrigger": "O", "EventArgument": "I-ZAMAN"}, {"Token": "d\u00f6nemine", "EventTrigger": "O", "EventArgument": "I-ZAMAN"}, {"Token": "oranla", "EventTrigger": "O", "EventArgument": "O"}, {"Token": "y\u00fczde", "EventTrigger": "O", "EventArgument": "B-ORAN"}, {"Token": "7.1", "EventTrigger": "O", "EventArgument": "I-ORAN"}, {"Token": "artarak4.97", "EventTrigger": "Gelir-Art\u0131\u015f", "EventArgument": "O"}, {"Token": "milyar", "EventTrigger": "O", "EventArgument": "I-PARA"}, {"Token": "euro", "EventTrigger": "O", "EventArgument": "I-PARA"}, {"Token": "oldu", "EventTrigger": "O", "EventArgument": "O"}, {"Token": ".", "EventTrigger": "O", "EventArgument": "O"}]}, {"SentenceId": "6", "SentenceText": "Asya-Pasifik b\u00f6lgesinde \u015firketin \u00fcr\u00fcnlerine olan talebin y\u00fczde 4.8 artmas\u0131dikkat \u00e7ekerken , Amerika k\u0131tas\u0131nda sat\u0131\u015flar y\u00fczde 4.4 artt\u0131 .", "Tokens": [{"Token": "Asya-Pasifik", "EventTrigger": "O", "EventArgument": "O"}, {"Token": "b\u00f6lgesinde", "EventTrigger": "O", "EventArgument": "O"}, {"Token": "\u015firketin", "EventTrigger": "O", "EventArgument": "O"}, {"Token": "\u00fcr\u00fcnlerine", "EventTrigger": "O", "EventArgument": "O"}, {"Token": "olan", "EventTrigger": "O", "EventArgument": "O"}, {"Token": "talebin", "EventTrigger": "O", "EventArgument": "O"}, {"Token": "y\u00fczde", "EventTrigger": "O", "EventArgument": "B-ORAN"}, {"Token": "4.8", "EventTrigger": "O", "EventArgument": "I-ORAN"}, {"Token": "artmas\u0131dikkat", "EventTrigger": "O", "EventArgument": "O"}, {"Token": "\u00e7ekerken", "EventTrigger": "O", "EventArgument": "O"}, {"Token": ",", "EventTrigger": "O", "EventArgument": "O"}, {"Token": "Amerika", "EventTrigger": "O", "EventArgument": "O"}, {"Token": "k\u0131tas\u0131nda", "EventTrigger": "O", "EventArgument": "O"}, {"Token": "sat\u0131\u015flar", "EventTrigger": "\u00dcr\u00fcn-Satma", "EventArgument": "O"}, {"Token": "y\u00fczde", "EventTrigger": "O", "EventArgument": "B-ORAN"}, {"Token": "4.4", "EventTrigger": "O", "EventArgument": "I-ORAN"}, {"Token": "artt\u0131", "EventTrigger": "O", "EventArgument": "O"}, {"Token": ".", "EventTrigger": "O", "EventArgument": "O"}]}, {"SentenceId": "7", "SentenceText": "Afrika veOrtado\u011fu'da da Heineken biras\u0131na y\u00f6nelik talebin y\u00fczde 3.5 artt\u0131\u011f\u0131 g\u00f6zlendi .", "Tokens": [{"Token": "Afrika", "EventTrigger": "O", "EventArgument": "O"}, {"Token": "veOrtado\u011fu'da", "EventTrigger": "O", "EventArgument": "O"}, {"Token": "da", "EventTrigger": "O", "EventArgument": "O"}, {"Token": "Heineken", "EventTrigger": "O", "EventArgument": "O"}, {"Token": "biras\u0131na", "EventTrigger": "O", "EventArgument": "O"}, {"Token": "y\u00f6nelik", "EventTrigger": "O", "EventArgument": "O"}, {"Token": "talebin", "EventTrigger": "O", "EventArgument": "O"}, {"Token": "y\u00fczde", "EventTrigger": "O", "EventArgument": "O"}, {"Token": "3.5", "EventTrigger": "O", "EventArgument": "O"}, {"Token": "artt\u0131\u011f\u0131", "EventTrigger": "O", "EventArgument": "O"}, {"Token": "g\u00f6zlendi", "EventTrigger": "O", "EventArgument": "O"}, {"Token": ".", "EventTrigger": "O", "EventArgument": "O"}]}, {"SentenceId": "8", "SentenceText": "Fakat Hollanda , \u0130ngiltere ve Portekiz'de zay\u0131f talep , Heineken'in Bat\u0131Avrupa sat\u0131\u015flar\u0131n\u0131n y\u0131ll\u0131k bazda y\u00fczde 21 d\u00fc\u015fmesine yol a\u00e7t\u0131 .", "Tokens": [{"Token": "Fakat", "EventTrigger": "O", "EventArgument": "O"}, {"Token": "Hollanda", "EventTrigger": "O", "EventArgument": "B-YER"}, {"Token": ",", "EventTrigger": "O", "EventArgument": "O"}, {"Token": "\u0130ngiltere", "EventTrigger": "O", "EventArgument": "B-YER"}, {"Token": "ve", "EventTrigger": "O", "EventArgument": "O"}, {"Token": "Portekiz'de", "EventTrigger": "O", "EventArgument": "B-YER"}, {"Token": "zay\u0131f", "EventTrigger": "O", "EventArgument": "O"}, {"Token": "talep", "EventTrigger": "O", "EventArgument": "O"}, {"Token": ",", "EventTrigger": "O", "EventArgument": "O"}, {"Token": "Heineken'in", "EventTrigger": "O", "EventArgument": "B-\u015e\u0130RKET"}, {"Token": "Bat\u0131Avrupa", "EventTrigger": "O", "EventArgument": "O"}, {"Token": "sat\u0131\u015flar\u0131n\u0131n", "EventTrigger": "\u00dcr\u00fcn-Satma", "EventArgument": "O"}, {"Token": "y\u0131ll\u0131k", "EventTrigger": "O", "EventArgument": "B-ZAMAN"}, {"Token": "bazda", "EventTrigger": "O", "EventArgument": "O"}, {"Token": "y\u00fczde", "EventTrigger": "O", "EventArgument": "B-ORAN"}, {"Token": "21", "EventTrigger": "O", "EventArgument": "I-ORAN"}, {"Token": "d\u00fc\u015fmesine", "EventTrigger": "O", "EventArgument": "O"}, {"Token": "yol", "EventTrigger": "O", "EventArgument": "O"}, {"Token": "a\u00e7t\u0131", "EventTrigger": "O", "EventArgument": "O"}, {"Token": ".", "EventTrigger": "O", "EventArgument": "O"}]}, {"SentenceId": "9", "SentenceText": "Portekiz'de sat\u0131\u015flar\u0131n `` \u00e7ift haneli bir oranda '' d\u00fc\u015ft\u00fc\u011f\u00fc a\u00e7\u0131kland\u0131 .", "Tokens": [{"Token": "Portekiz'de", "EventTrigger": "O", "EventArgument": "B-YER"}, {"Token": "sat\u0131\u015flar\u0131n", "EventTrigger": "\u00dcr\u00fcn-Satma", "EventArgument": "O"}, {"Token": "``", "EventTrigger": "O", "EventArgument": "O"}, {"Token": "\u00e7ift", "EventTrigger": "O", "EventArgument": "O"}, {"Token": "haneli", "EventTrigger": "O", "EventArgument": "O"}, {"Token": "bir", "EventTrigger": "O", "EventArgument": "O"}, {"Token": "oranda", "EventTrigger": "O", "EventArgument": "O"}, {"Token": "''", "EventTrigger": "O", "EventArgument": "O"}, {"Token": "d\u00fc\u015ft\u00fc\u011f\u00fc", "EventTrigger": "O", "EventArgument": "O"}, {"Token": "a\u00e7\u0131kland\u0131", "EventTrigger": "O", "EventArgument": "O"}, {"Token": ".", "EventTrigger": "O", "EventArgument": "O"}]}, {"SentenceId": "10", "SentenceText": "\u0130ngiltere , Hollandave \u0130spanya'da ise sat\u0131\u015flardaki d\u00fc\u015f\u00fc\u015f tek haneli oldu .", "Tokens": [{"Token": "\u0130ngiltere", "EventTrigger": "O", "EventArgument": "B-YER"}, {"Token": ",", "EventTrigger": "O", "EventArgument": "O"}, {"Token": "Hollandave", "EventTrigger": "O", "EventArgument": "B-YER"}, {"Token": "\u0130spanya'da", "EventTrigger": "O", "EventArgument": "B-YER"}, {"Token": "ise", "EventTrigger": "O", "EventArgument": "O"}, {"Token": "sat\u0131\u015flardaki", "EventTrigger": "\u00dcr\u00fcn-Satma", "EventArgument": "O"}, {"Token": "d\u00fc\u015f\u00fc\u015f", "EventTrigger": "O", "EventArgument": "O"}, {"Token": "tek", "EventTrigger": "O", "EventArgument": "O"}, {"Token": "haneli", "EventTrigger": "O", "EventArgument": "O"}, {"Token": "oldu", "EventTrigger": "O", "EventArgument": "O"}, {"Token": ".", "EventTrigger": "O", "EventArgument": "O"}]}, {"SentenceId": "11", "SentenceText": "Cannacord Genuity analisti Eddy Hargreaves , bug\u00fcn a\u00e7\u0131klanan rakamlar\u0131n '' Amerika k\u0131tas\u0131 hari\u00e7 bir\u00e7ok b\u00f6lgede artan bask\u0131ya i\u015faret etti\u011fini '' dilegetirdi .", "Tokens": [{"Token": "Cannacord", "EventTrigger": "O", "EventArgument": "O"}, {"Token": "Genuity", "EventTrigger": "O", "EventArgument": "O"}, {"Token": "analisti", "EventTrigger": "O", "EventArgument": "O"}, {"Token": "Eddy", "EventTrigger": "O", "EventArgument": "O"}, {"Token": "Hargreaves", "EventTrigger": "O", "EventArgument": "O"}, {"Token": ",", "EventTrigger": "O", "EventArgument": "O"}, {"Token": "bug\u00fcn", "EventTrigger": "O", "EventArgument": "O"}, {"Token": "a\u00e7\u0131klanan", "EventTrigger": "O", "EventArgument": "O"}, {"Token": "rakamlar\u0131n", "EventTrigger": "O", "EventArgument": "O"}, {"Token": "''", "EventTrigger": "O", "EventArgument": "O"}, {"Token": "Amerika", "EventTrigger": "O", "EventArgument": "O"}, {"Token": "k\u0131tas\u0131", "EventTrigger": "O", "EventArgument": "O"}, {"Token": "hari\u00e7", "EventTrigger": "O", "EventArgument": "O"}, {"Token": "bir\u00e7ok", "EventTrigger": "O", "EventArgument": "O"}, {"Token": "b\u00f6lgede", "EventTrigger": "O", "EventArgument": "O"}, {"Token": "artan", "EventTrigger": "O", "EventArgument": "O"}, {"Token": "bask\u0131ya", "EventTrigger": "O", "EventArgument": "O"}, {"Token": "i\u015faret", "EventTrigger": "O", "EventArgument": "O"}, {"Token": "etti\u011fini", "EventTrigger": "O", "EventArgument": "O"}, {"Token": "''", "EventTrigger": "O", "EventArgument": "O"}, {"Token": "dilegetirdi", "EventTrigger": "O", "EventArgument": "O"}, {"Token": ".", "EventTrigger": "O", "EventArgument": "O"}]}, {"SentenceId": "12", "SentenceText": "Bloomberg'e konu\u015fan analist , \u00f6zellikla Bat\u0131 Avrupa ile ilgiliolarak kayg\u0131l\u0131 oldu\u011funu belirtti .", "Tokens": [{"Token": "Bloomberg'e", "EventTrigger": "O", "EventArgument": "O"}, {"Token": "konu\u015fan", "EventTrigger": "O", "EventArgument": "O"}, {"Token": "analist", "EventTrigger": "O", "EventArgument": "O"}, {"Token": ",", "EventTrigger": "O", "EventArgument": "O"}, {"Token": "\u00f6zellikla", "EventTrigger": "O", "EventArgument": "O"}, {"Token": "Bat\u0131", "EventTrigger": "O", "EventArgument": "O"}, {"Token": "Avrupa", "EventTrigger": "O", "EventArgument": "O"}, {"Token": "ile", "EventTrigger": "O", "EventArgument": "O"}, {"Token": "ilgiliolarak", "EventTrigger": "O", "EventArgument": "O"}, {"Token": "kayg\u0131l\u0131", "EventTrigger": "O", "EventArgument": "O"}, {"Token": "oldu\u011funu", "EventTrigger": "O", "EventArgument": "O"}, {"Token": "belirtti", "EventTrigger": "O", "EventArgument": "O"}, {"Token": ".", "EventTrigger": "O", "EventArgument": "O"}]}, {"SentenceId": "13", "SentenceText": "Hargreaves , \u015firketin son James Bond filmiSkyfall ile ba\u015flayan reklam ata\u011f\u0131n\u0131n `` yeterli olmayabilece\u011fini '' ekledi .", "Tokens": [{"Token": "Hargreaves", "EventTrigger": "O", "EventArgument": "B-\u015e\u0130RKET"}, {"Token": ",", "EventTrigger": "O", "EventArgument": "O"}, {"Token": "\u015firketin", "EventTrigger": "O", "EventArgument": "O"}, {"Token": "son", "EventTrigger": "O", "EventArgument": "O"}, {"Token": "James", "EventTrigger": "O", "EventArgument": "O"}, {"Token": "Bond", "EventTrigger": "O", "EventArgument": "O"}, {"Token": "filmiSkyfall", "EventTrigger": "O", "EventArgument": "O"}, {"Token": "ile", "EventTrigger": "O", "EventArgument": "O"}, {"Token": "ba\u015flayan", "EventTrigger": "O", "EventArgument": "O"}, {"Token": "reklam", "EventTrigger": "Marka-Reklam", "EventArgument": "O"}, {"Token": "ata\u011f\u0131n\u0131n", "EventTrigger": "O", "EventArgument": "O"}, {"Token": "``", "EventTrigger": "O", "EventArgument": "O"}, {"Token": "yeterli", "EventTrigger": "O", "EventArgument": "O"}, {"Token": "olmayabilece\u011fini", "EventTrigger": "O", "EventArgument": "O"}, {"Token": "''", "EventTrigger": "O", "EventArgument": "O"}, {"Token": "ekledi", "EventTrigger": "O", "EventArgument": "O"}, {"Token": ".", "EventTrigger": "O", "EventArgument": "O"}]}, {"SentenceId": "14", "SentenceText": "Heineken , 2012 y\u0131l\u0131n\u0131n tamam\u0131nda , ge\u00e7en y\u0131lki 1.58 milyar Euro civar\u0131ndakar bekledi\u011fini a\u00e7\u0131klad\u0131.\u015eirketin hisseleri , sabah saatlerinde Amsterdam borsas\u0131nda y\u00fczde 2.5 de\u011ferkaybetmi\u015fti .", "Tokens": [{"Token": "Heineken", "EventTrigger": "O", "EventArgument": "B-\u015e\u0130RKET"}, {"Token": ",", "EventTrigger": "O", "EventArgument": "O"}, {"Token": "2012", "EventTrigger": "O", "EventArgument": "B-ZAMAN"}, {"Token": "y\u0131l\u0131n\u0131n", "EventTrigger": "O", "EventArgument": "I-ZAMAN"}, {"Token": "tamam\u0131nda", "EventTrigger": "O", "EventArgument": "O"}, {"Token": ",", "EventTrigger": "O", "EventArgument": "O"}, {"Token": "ge\u00e7en", "EventTrigger": "O", "EventArgument": "B-ZAMAN"}, {"Token": "y\u0131lki", "EventTrigger": "O", "EventArgument": "I-ZAMAN"}, {"Token": "1.58", "EventTrigger": "O", "EventArgument": "B-PARA"}, {"Token": "milyar", "EventTrigger": "O", "EventArgument": "I-PARA"}, {"Token": "Euro", "EventTrigger": "O", "EventArgument": "I-PARA"}, {"Token": "civar\u0131ndakar", "EventTrigger": "O", "EventArgument": "O"}, {"Token": "bekledi\u011fini", "EventTrigger": "O", "EventArgument": "O"}, {"Token": "a\u00e7\u0131klad\u0131.\u015eirketin", "EventTrigger": "O", "EventArgument": "O"}, {"Token": "hisseleri", "EventTrigger": "O", "EventArgument": "O"}, {"Token": ",", "EventTrigger": "O", "EventArgument": "O"}, {"Token": "sabah", "EventTrigger": "O", "EventArgument": "O"}, {"Token": "saatlerinde", "EventTrigger": "O", "EventArgument": "O"}, {"Token": "Amsterdam", "EventTrigger": "O", "EventArgument": "O"}, {"Token": "borsas\u0131nda", "EventTrigger": "O", "EventArgument": "O"}, {"Token": "y\u00fczde", "EventTrigger": "O", "EventArgument": "O"}, {"Token": "2.5", "EventTrigger": "O", "EventArgument": "O"}, {"Token": "de\u011ferkaybetmi\u015fti", "EventTrigger": "O", "EventArgument": "O"}, {"Token": ".", "EventTrigger": "O", "EventArgument": "O"}]}]}