{"DocId": 1619, "Sentences": [{"SentenceId": "1", "SentenceText": "SPK iki \u015firketi sermaye piyasas\u0131 kanunu kapsam\u0131ndan \u00e7\u0131kard\u0131 .", "Tokens": [{"Token": "SPK", "EventTrigger": "O", "EventArgument": "O"}, {"Token": "iki", "EventTrigger": "O", "EventArgument": "O"}, {"Token": "\u015firketi", "EventTrigger": "O", "EventArgument": "O"}, {"Token": "sermaye", "EventTrigger": "O", "EventArgument": "O"}, {"Token": "piyasas\u0131", "EventTrigger": "O", "EventArgument": "O"}, {"Token": "kanunu", "EventTrigger": "O", "EventArgument": "O"}, {"Token": "kapsam\u0131ndan", "EventTrigger": "O", "EventArgument": "O"}, {"Token": "\u00e7\u0131kard\u0131", "EventTrigger": "O", "EventArgument": "O"}, {"Token": ".", "EventTrigger": "O", "EventArgument": "O"}]}, {"SentenceId": "2", "SentenceText": "SPK B\u00fclteni'nde yer alan duyuruya g\u00f6re , iki \u015firketin Sermaye Piyasas\u0131 Kanun Kapsam\u0131'ndan \u00e7\u0131kar\u0131lmas\u0131na karar verildi .", "Tokens": [{"Token": "SPK", "EventTrigger": "O", "EventArgument": "O"}, {"Token": "B\u00fclteni'nde", "EventTrigger": "O", "EventArgument": "O"}, {"Token": "yer", "EventTrigger": "O", "EventArgument": "O"}, {"Token": "alan", "EventTrigger": "O", "EventArgument": "O"}, {"Token": "duyuruya", "EventTrigger": "O", "EventArgument": "O"}, {"Token": "g\u00f6re", "EventTrigger": "O", "EventArgument": "O"}, {"Token": ",", "EventTrigger": "O", "EventArgument": "O"}, {"Token": "iki", "EventTrigger": "O", "EventArgument": "O"}, {"Token": "\u015firketin", "EventTrigger": "O", "EventArgument": "O"}, {"Token": "Sermaye", "EventTrigger": "O", "EventArgument": "O"}, {"Token": "Piyasas\u0131", "EventTrigger": "O", "EventArgument": "O"}, {"Token": "Kanun", "EventTrigger": "O", "EventArgument": "O"}, {"Token": "Kapsam\u0131'ndan", "EventTrigger": "O", "EventArgument": "O"}, {"Token": "\u00e7\u0131kar\u0131lmas\u0131na", "EventTrigger": "O", "EventArgument": "O"}, {"Token": "karar", "EventTrigger": "O", "EventArgument": "O"}, {"Token": "verildi", "EventTrigger": "O", "EventArgument": "O"}, {"Token": ".", "EventTrigger": "O", "EventArgument": "O"}]}, {"SentenceId": "3", "SentenceText": "SPK B\u00fclteni yay\u0131nland\u0131 .", "Tokens": [{"Token": "SPK", "EventTrigger": "O", "EventArgument": "O"}, {"Token": "B\u00fclteni", "EventTrigger": "O", "EventArgument": "O"}, {"Token": "yay\u0131nland\u0131", "EventTrigger": "O", "EventArgument": "O"}, {"Token": ".", "EventTrigger": "O", "EventArgument": "O"}]}, {"SentenceId": "4", "SentenceText": "B\u00fclten'de yer alan duyuruya g\u00f6re , Kanun kapsam\u0131ndan \u00e7\u0131kar\u0131lmak i\u00e7in ba\u015fvuruda bulunan Reel Yat\u0131r\u0131m Holding A.\u015e .", "Tokens": [{"Token": "B\u00fclten'de", "EventTrigger": "O", "EventArgument": "O"}, {"Token": "yer", "EventTrigger": "O", "EventArgument": "O"}, {"Token": "alan", "EventTrigger": "O", "EventArgument": "O"}, {"Token": "duyuruya", "EventTrigger": "O", "EventArgument": "O"}, {"Token": "g\u00f6re", "EventTrigger": "O", "EventArgument": "O"}, {"Token": ",", "EventTrigger": "O", "EventArgument": "O"}, {"Token": "Kanun", "EventTrigger": "O", "EventArgument": "O"}, {"Token": "kapsam\u0131ndan", "EventTrigger": "O", "EventArgument": "O"}, {"Token": "\u00e7\u0131kar\u0131lmak", "EventTrigger": "O", "EventArgument": "O"}, {"Token": "i\u00e7in", "EventTrigger": "O", "EventArgument": "O"}, {"Token": "ba\u015fvuruda", "EventTrigger": "O", "EventArgument": "O"}, {"Token": "bulunan", "EventTrigger": "O", "EventArgument": "O"}, {"Token": "Reel", "EventTrigger": "O", "EventArgument": "O"}, {"Token": "Yat\u0131r\u0131m", "EventTrigger": "O", "EventArgument": "O"}, {"Token": "Holding", "EventTrigger": "O", "EventArgument": "O"}, {"Token": "A.\u015e", "EventTrigger": "O", "EventArgument": "O"}, {"Token": ".", "EventTrigger": "O", "EventArgument": "O"}]}, {"SentenceId": "5", "SentenceText": "ve Aktenta\u015f Aksaray Tar\u0131m End\u00fcstri Ticaret A.\u015e .", "Tokens": [{"Token": "ve", "EventTrigger": "O", "EventArgument": "O"}, {"Token": "Aktenta\u015f", "EventTrigger": "O", "EventArgument": "O"}, {"Token": "Aksaray", "EventTrigger": "O", "EventArgument": "O"}, {"Token": "Tar\u0131m", "EventTrigger": "O", "EventArgument": "O"}, {"Token": "End\u00fcstri", "EventTrigger": "O", "EventArgument": "O"}, {"Token": "Ticaret", "EventTrigger": "O", "EventArgument": "O"}, {"Token": "A.\u015e", "EventTrigger": "O", "EventArgument": "O"}, {"Token": ".", "EventTrigger": "O", "EventArgument": "O"}]}, {"SentenceId": "6", "SentenceText": "'nin ba\u015fvurusu onayland\u0131 .", "Tokens": [{"Token": "'nin", "EventTrigger": "O", "EventArgument": "O"}, {"Token": "ba\u015fvurusu", "EventTrigger": "O", "EventArgument": "O"}, {"Token": "onayland\u0131", "EventTrigger": "O", "EventArgument": "O"}, {"Token": ".", "EventTrigger": "O", "EventArgument": "O"}]}, {"SentenceId": "7", "SentenceText": "Buna g\u00f6re ; Reel Yat\u0131r\u0131m Holding A.\u015e .", "Tokens": [{"Token": "Buna", "EventTrigger": "O", "EventArgument": "O"}, {"Token": "g\u00f6re", "EventTrigger": "O", "EventArgument": "O"}, {"Token": ";", "EventTrigger": "O", "EventArgument": "O"}, {"Token": "Reel", "EventTrigger": "O", "EventArgument": "O"}, {"Token": "Yat\u0131r\u0131m", "EventTrigger": "O", "EventArgument": "O"}, {"Token": "Holding", "EventTrigger": "O", "EventArgument": "O"}, {"Token": "A.\u015e", "EventTrigger": "O", "EventArgument": "O"}, {"Token": ".", "EventTrigger": "O", "EventArgument": "O"}]}, {"SentenceId": "8", "SentenceText": "'nin II-16.1 say\u0131l\u0131 Ortakl\u0131klar\u0131n Kanun Kapsam\u0131ndan \u00c7\u0131kar\u0131lmas\u0131 ve Paylar\u0131n\u0131n Borsada \u0130\u015flem G\u00f6rmesi Zorunlulu\u011funa \u0130li\u015fkin Esaslar Tebli\u011fi \u2019 nin 6 \u2019 nc\u0131 maddesi uyar\u0131nca sermayesinin y\u00fczde doksan be\u015finden daha fazlas\u0131n\u0131n en fazla elli pay sahibine ait olmas\u0131 gerek\u00e7esiyleAktenta\u015f Aksaray Tar\u0131m End\u00fcstri Ticaret A.\u015e .", "Tokens": [{"Token": "'nin", "EventTrigger": "O", "EventArgument": "O"}, {"Token": "II-16.1", "EventTrigger": "O", "EventArgument": "O"}, {"Token": "say\u0131l\u0131", "EventTrigger": "O", "EventArgument": "O"}, {"Token": "Ortakl\u0131klar\u0131n", "EventTrigger": "O", "EventArgument": "O"}, {"Token": "Kanun", "EventTrigger": "O", "EventArgument": "O"}, {"Token": "Kapsam\u0131ndan", "EventTrigger": "O", "EventArgument": "O"}, {"Token": "\u00c7\u0131kar\u0131lmas\u0131", "EventTrigger": "O", "EventArgument": "O"}, {"Token": "ve", "EventTrigger": "O", "EventArgument": "O"}, {"Token": "Paylar\u0131n\u0131n", "EventTrigger": "O", "EventArgument": "O"}, {"Token": "Borsada", "EventTrigger": "O", "EventArgument": "O"}, {"Token": "\u0130\u015flem", "EventTrigger": "Borsa-\u0130\u015flem_G\u00f6rme", "EventArgument": "O"}, {"Token": "G\u00f6rmesi", "EventTrigger": "Borsa-\u0130\u015flem_G\u00f6rme", "EventArgument": "O"}, {"Token": "Zorunlulu\u011funa", "EventTrigger": "O", "EventArgument": "O"}, {"Token": "\u0130li\u015fkin", "EventTrigger": "O", "EventArgument": "O"}, {"Token": "Esaslar", "EventTrigger": "O", "EventArgument": "O"}, {"Token": "Tebli\u011fi", "EventTrigger": "O", "EventArgument": "O"}, {"Token": "\u2019", "EventTrigger": "O", "EventArgument": "O"}, {"Token": "nin", "EventTrigger": "O", "EventArgument": "O"}, {"Token": "6", "EventTrigger": "O", "EventArgument": "O"}, {"Token": "\u2019", "EventTrigger": "O", "EventArgument": "O"}, {"Token": "nc\u0131", "EventTrigger": "O", "EventArgument": "O"}, {"Token": "maddesi", "EventTrigger": "O", "EventArgument": "O"}, {"Token": "uyar\u0131nca", "EventTrigger": "O", "EventArgument": "O"}, {"Token": "sermayesinin", "EventTrigger": "O", "EventArgument": "O"}, {"Token": "y\u00fczde", "EventTrigger": "O", "EventArgument": "O"}, {"Token": "doksan", "EventTrigger": "O", "EventArgument": "O"}, {"Token": "be\u015finden", "EventTrigger": "O", "EventArgument": "O"}, {"Token": "daha", "EventTrigger": "O", "EventArgument": "O"}, {"Token": "fazlas\u0131n\u0131n", "EventTrigger": "O", "EventArgument": "O"}, {"Token": "en", "EventTrigger": "O", "EventArgument": "O"}, {"Token": "fazla", "EventTrigger": "O", "EventArgument": "O"}, {"Token": "elli", "EventTrigger": "O", "EventArgument": "O"}, {"Token": "pay", "EventTrigger": "O", "EventArgument": "O"}, {"Token": "sahibine", "EventTrigger": "O", "EventArgument": "O"}, {"Token": "ait", "EventTrigger": "O", "EventArgument": "O"}, {"Token": "olmas\u0131", "EventTrigger": "O", "EventArgument": "O"}, {"Token": "gerek\u00e7esiyleAktenta\u015f", "EventTrigger": "O", "EventArgument": "O"}, {"Token": "Aksaray", "EventTrigger": "O", "EventArgument": "O"}, {"Token": "Tar\u0131m", "EventTrigger": "O", "EventArgument": "O"}, {"Token": "End\u00fcstri", "EventTrigger": "O", "EventArgument": "O"}, {"Token": "Ticaret", "EventTrigger": "O", "EventArgument": "O"}, {"Token": "A.\u015e", "EventTrigger": "O", "EventArgument": "O"}, {"Token": ".", "EventTrigger": "O", "EventArgument": "O"}]}, {"SentenceId": "9", "SentenceText": "'nin ise II-16.1 say\u0131l\u0131 Ortakl\u0131klar\u0131n Kanun Kapsam\u0131ndan \u00c7\u0131kar\u0131lmas\u0131 ve Paylar\u0131n\u0131n Borsada \u0130\u015flem G\u00f6rmesi Zorunlulu\u011funa \u0130li\u015fkin Esaslar Tebli\u011fi \u2019 nin 5 inci maddesi \u00e7er\u00e7evesinde genel kurul karar\u0131 al\u0131nmas\u0131 gerek\u00e7esiyle Kanun kapsam\u0131ndan \u00e7\u0131kar\u0131lmas\u0131na karar verildi .", "Tokens": [{"Token": "'nin", "EventTrigger": "O", "EventArgument": "O"}, {"Token": "ise", "EventTrigger": "O", "EventArgument": "O"}, {"Token": "II-16.1", "EventTrigger": "O", "EventArgument": "O"}, {"Token": "say\u0131l\u0131", "EventTrigger": "O", "EventArgument": "O"}, {"Token": "Ortakl\u0131klar\u0131n", "EventTrigger": "O", "EventArgument": "O"}, {"Token": "Kanun", "EventTrigger": "O", "EventArgument": "O"}, {"Token": "Kapsam\u0131ndan", "EventTrigger": "O", "EventArgument": "O"}, {"Token": "\u00c7\u0131kar\u0131lmas\u0131", "EventTrigger": "O", "EventArgument": "O"}, {"Token": "ve", "EventTrigger": "O", "EventArgument": "O"}, {"Token": "Paylar\u0131n\u0131n", "EventTrigger": "O", "EventArgument": "O"}, {"Token": "Borsada", "EventTrigger": "O", "EventArgument": "O"}, {"Token": "\u0130\u015flem", "EventTrigger": "Borsa-\u0130\u015flem_G\u00f6rme", "EventArgument": "O"}, {"Token": "G\u00f6rmesi", "EventTrigger": "Borsa-\u0130\u015flem_G\u00f6rme", "EventArgument": "O"}, {"Token": "Zorunlulu\u011funa", "EventTrigger": "O", "EventArgument": "O"}, {"Token": "\u0130li\u015fkin", "EventTrigger": "O", "EventArgument": "O"}, {"Token": "Esaslar", "EventTrigger": "O", "EventArgument": "O"}, {"Token": "Tebli\u011fi", "EventTrigger": "O", "EventArgument": "O"}, {"Token": "\u2019", "EventTrigger": "O", "EventArgument": "O"}, {"Token": "nin", "EventTrigger": "O", "EventArgument": "O"}, {"Token": "5", "EventTrigger": "O", "EventArgument": "O"}, {"Token": "inci", "EventTrigger": "O", "EventArgument": "O"}, {"Token": "maddesi", "EventTrigger": "O", "EventArgument": "O"}, {"Token": "\u00e7er\u00e7evesinde", "EventTrigger": "O", "EventArgument": "O"}, {"Token": "genel", "EventTrigger": "O", "EventArgument": "O"}, {"Token": "kurul", "EventTrigger": "O", "EventArgument": "O"}, {"Token": "karar\u0131", "EventTrigger": "O", "EventArgument": "O"}, {"Token": "al\u0131nmas\u0131", "EventTrigger": "O", "EventArgument": "O"}, {"Token": "gerek\u00e7esiyle", "EventTrigger": "O", "EventArgument": "O"}, {"Token": "Kanun", "EventTrigger": "O", "EventArgument": "O"}, {"Token": "kapsam\u0131ndan", "EventTrigger": "O", "EventArgument": "O"}, {"Token": "\u00e7\u0131kar\u0131lmas\u0131na", "EventTrigger": "O", "EventArgument": "O"}, {"Token": "karar", "EventTrigger": "O", "EventArgument": "O"}, {"Token": "verildi", "EventTrigger": "O", "EventArgument": "O"}, {"Token": ".", "EventTrigger": "O", "EventArgument": "O"}]}]}