{"DocId": 11576, "Sentences": [{"SentenceId": "1", "SentenceText": "Aselsan'\u0131n notu g\u00fcncellendi .", "Tokens": [{"Token": "Aselsan'\u0131n", "EventTrigger": "O", "EventArgument": "B-\u015e\u0130RKET"}, {"Token": "notu", "EventTrigger": "Finansal_Sonu\u00e7-Kredi_Notu", "EventArgument": "O"}, {"Token": "g\u00fcncellendi", "EventTrigger": "O", "EventArgument": "O"}, {"Token": ".", "EventTrigger": "O", "EventArgument": "O"}]}, {"SentenceId": "2", "SentenceText": "Aselsan'\u0131n Kurumsal Y\u00f6netim Derecelendirme d\u00f6nem revizyonu raporu a\u00e7\u0131kland\u0131 .", "Tokens": [{"Token": "Aselsan'\u0131n", "EventTrigger": "O", "EventArgument": "B-\u015e\u0130RKET"}, {"Token": "Kurumsal", "EventTrigger": "O", "EventArgument": "O"}, {"Token": "Y\u00f6netim", "EventTrigger": "O", "EventArgument": "O"}, {"Token": "Derecelendirme", "EventTrigger": "O", "EventArgument": "O"}, {"Token": "d\u00f6nem", "EventTrigger": "O", "EventArgument": "O"}, {"Token": "revizyonu", "EventTrigger": "O", "EventArgument": "O"}, {"Token": "raporu", "EventTrigger": "Analist-Raporlama", "EventArgument": "O"}, {"Token": "a\u00e7\u0131kland\u0131", "EventTrigger": "O", "EventArgument": "O"}, {"Token": ".", "EventTrigger": "O", "EventArgument": "O"}]}]}