{"DocId": 1857, "Sentences": [{"SentenceId": "1", "SentenceText": "Makina Tak\u0131m'dan y\u00fczde100 bedelli art\u0131r\u0131m .", "Tokens": [{"Token": "Makina", "EventTrigger": "O", "EventArgument": "O"}, {"Token": "Tak\u0131m'dan", "EventTrigger": "O", "EventArgument": "O"}, {"Token": "y\u00fczde100", "EventTrigger": "O", "EventArgument": "O"}, {"Token": "bedelli", "EventTrigger": "O", "EventArgument": "O"}, {"Token": "art\u0131r\u0131m", "EventTrigger": "O", "EventArgument": "O"}, {"Token": ".", "EventTrigger": "O", "EventArgument": "O"}]}, {"SentenceId": "2", "SentenceText": "Makina Tak\u0131m'\u0131n y\u00fczde 100 bedelli art\u0131r\u0131m\u0131na onay \u00e7\u0131kt\u0131 .", "Tokens": [{"Token": "Makina", "EventTrigger": "O", "EventArgument": "O"}, {"Token": "Tak\u0131m'\u0131n", "EventTrigger": "O", "EventArgument": "O"}, {"Token": "y\u00fczde", "EventTrigger": "O", "EventArgument": "O"}, {"Token": "100", "EventTrigger": "O", "EventArgument": "O"}, {"Token": "bedelli", "EventTrigger": "O", "EventArgument": "O"}, {"Token": "art\u0131r\u0131m\u0131na", "EventTrigger": "O", "EventArgument": "O"}, {"Token": "onay", "EventTrigger": "O", "EventArgument": "O"}, {"Token": "\u00e7\u0131kt\u0131", "EventTrigger": "O", "EventArgument": "O"}, {"Token": ".", "EventTrigger": "O", "EventArgument": "O"}]}, {"SentenceId": "3", "SentenceText": "Makina Tak\u0131m End\u00fcstrisi A.\u015e .", "Tokens": [{"Token": "Makina", "EventTrigger": "O", "EventArgument": "O"}, {"Token": "Tak\u0131m", "EventTrigger": "O", "EventArgument": "O"}, {"Token": "End\u00fcstrisi", "EventTrigger": "O", "EventArgument": "O"}, {"Token": "A.\u015e", "EventTrigger": "O", "EventArgument": "O"}, {"Token": ".", "EventTrigger": "O", "EventArgument": "O"}]}, {"SentenceId": "4", "SentenceText": "taraf\u0131ndan KAP'a yap\u0131lan a\u00e7\u0131klamada , bedelli sermaye art\u0131r\u0131m\u0131 i\u00e7in SPK'ya yap\u0131lan ba\u015fvurunun onayland\u0131\u011f\u0131 bildirildi .", "Tokens": [{"Token": "taraf\u0131ndan", "EventTrigger": "O", "EventArgument": "O"}, {"Token": "KAP'a", "EventTrigger": "O", "EventArgument": "O"}, {"Token": "yap\u0131lan", "EventTrigger": "O", "EventArgument": "O"}, {"Token": "a\u00e7\u0131klamada", "EventTrigger": "O", "EventArgument": "O"}, {"Token": ",", "EventTrigger": "O", "EventArgument": "O"}, {"Token": "bedelli", "EventTrigger": "O", "EventArgument": "O"}, {"Token": "sermaye", "EventTrigger": "Sermaye-Artt\u0131rma", "EventArgument": "O"}, {"Token": "art\u0131r\u0131m\u0131", "EventTrigger": "Sermaye-Artt\u0131rma", "EventArgument": "O"}, {"Token": "i\u00e7in", "EventTrigger": "O", "EventArgument": "O"}, {"Token": "SPK'ya", "EventTrigger": "O", "EventArgument": "O"}, {"Token": "yap\u0131lan", "EventTrigger": "O", "EventArgument": "O"}, {"Token": "ba\u015fvurunun", "EventTrigger": "O", "EventArgument": "O"}, {"Token": "onayland\u0131\u011f\u0131", "EventTrigger": "O", "EventArgument": "O"}, {"Token": "bildirildi", "EventTrigger": "O", "EventArgument": "O"}, {"Token": ".", "EventTrigger": "O", "EventArgument": "O"}]}, {"SentenceId": "5", "SentenceText": "\u015eirketten gelen a\u00e7\u0131klama \u015f\u00f6yle ; \u015eirketimizin 200.000.000 TL kay\u0131tl\u0131 sermaye tavan\u0131 i\u00e7erisinde , 100.000.000 TL olan \u00e7\u0131kar\u0131lm\u0131\u015f sermayesinin % 100 oran\u0131nda , tamam\u0131 nakit kar\u015f\u0131l\u0131\u011f\u0131 olmak \u00fczere 200.000.000 TL's\u0131na \u00e7\u0131kart\u0131lmas\u0131na ili\u015fkin ba\u015fvurumuzun onayland\u0131\u011f\u0131 Sermaye Piyas\u0131s\u0131 Kurulu'nun 11.11.2016 tarih ve 2016/30 say\u0131l\u0131 SPK B\u00fclteni'nde duyurulmu\u015ftur .", "Tokens": [{"Token": "\u015eirketten", "EventTrigger": "O", "EventArgument": "O"}, {"Token": "gelen", "EventTrigger": "O", "EventArgument": "O"}, {"Token": "a\u00e7\u0131klama", "EventTrigger": "O", "EventArgument": "O"}, {"Token": "\u015f\u00f6yle", "EventTrigger": "O", "EventArgument": "O"}, {"Token": ";", "EventTrigger": "O", "EventArgument": "O"}, {"Token": "\u015eirketimizin", "EventTrigger": "O", "EventArgument": "O"}, {"Token": "200.000.000", "EventTrigger": "O", "EventArgument": "B-PARA"}, {"Token": "TL", "EventTrigger": "O", "EventArgument": "I-PARA"}, {"Token": "kay\u0131tl\u0131", "EventTrigger": "O", "EventArgument": "O"}, {"Token": "sermaye", "EventTrigger": "Sermaye-Tavan\u0131", "EventArgument": "O"}, {"Token": "tavan\u0131", "EventTrigger": "Sermaye-Tavan\u0131", "EventArgument": "O"}, {"Token": "i\u00e7erisinde", "EventTrigger": "O", "EventArgument": "O"}, {"Token": ",", "EventTrigger": "O", "EventArgument": "O"}, {"Token": "100.000.000", "EventTrigger": "O", "EventArgument": "B-PARA"}, {"Token": "TL", "EventTrigger": "O", "EventArgument": "I-PARA"}, {"Token": "olan", "EventTrigger": "O", "EventArgument": "O"}, {"Token": "\u00e7\u0131kar\u0131lm\u0131\u015f", "EventTrigger": "Sermaye-Artt\u0131rma", "EventArgument": "O"}, {"Token": "sermayesinin", "EventTrigger": "Sermaye-Artt\u0131rma", "EventArgument": "O"}, {"Token": "%", "EventTrigger": "O", "EventArgument": "B-ORAN"}, {"Token": "100", "EventTrigger": "O", "EventArgument": "I-ORAN"}, {"Token": "oran\u0131nda", "EventTrigger": "O", "EventArgument": "O"}, {"Token": ",", "EventTrigger": "O", "EventArgument": "O"}, {"Token": "tamam\u0131", "EventTrigger": "O", "EventArgument": "O"}, {"Token": "nakit", "EventTrigger": "O", "EventArgument": "O"}, {"Token": "kar\u015f\u0131l\u0131\u011f\u0131", "EventTrigger": "O", "EventArgument": "O"}, {"Token": "olmak", "EventTrigger": "O", "EventArgument": "O"}, {"Token": "\u00fczere", "EventTrigger": "O", "EventArgument": "O"}, {"Token": "200.000.000", "EventTrigger": "O", "EventArgument": "B-PARA"}, {"Token": "TL's\u0131na", "EventTrigger": "O", "EventArgument": "I-PARA"}, {"Token": "\u00e7\u0131kart\u0131lmas\u0131na", "EventTrigger": "Sermaye-Artt\u0131rma", "EventArgument": "O"}, {"Token": "ili\u015fkin", "EventTrigger": "O", "EventArgument": "O"}, {"Token": "ba\u015fvurumuzun", "EventTrigger": "O", "EventArgument": "O"}, {"Token": "onayland\u0131\u011f\u0131", "EventTrigger": "O", "EventArgument": "O"}, {"Token": "Sermaye", "EventTrigger": "O", "EventArgument": "O"}, {"Token": "Piyas\u0131s\u0131", "EventTrigger": "O", "EventArgument": "O"}, {"Token": "Kurulu'nun", "EventTrigger": "O", "EventArgument": "O"}, {"Token": "11.11.2016", "EventTrigger": "O", "EventArgument": "O"}, {"Token": "tarih", "EventTrigger": "O", "EventArgument": "O"}, {"Token": "ve", "EventTrigger": "O", "EventArgument": "O"}, {"Token": "2016/30", "EventTrigger": "O", "EventArgument": "O"}, {"Token": "say\u0131l\u0131", "EventTrigger": "O", "EventArgument": "O"}, {"Token": "SPK", "EventTrigger": "O", "EventArgument": "O"}, {"Token": "B\u00fclteni'nde", "EventTrigger": "O", "EventArgument": "O"}, {"Token": "duyurulmu\u015ftur", "EventTrigger": "O", "EventArgument": "O"}, {"Token": ".", "EventTrigger": "O", "EventArgument": "O"}]}]}