{"DocId": 22237, "Sentences": [{"SentenceId": "1", "SentenceText": "Trabzonspor gelirde de lider .", "Tokens": [{"Token": "Trabzonspor", "EventTrigger": "O", "EventArgument": "B-\u015e\u0130RKET"}, {"Token": "gelirde", "EventTrigger": "Gelir-Duyuru", "EventArgument": "O"}, {"Token": "de", "EventTrigger": "O", "EventArgument": "O"}, {"Token": "lider", "EventTrigger": "O", "EventArgument": "O"}, {"Token": ".", "EventTrigger": "O", "EventArgument": "O"}]}, {"SentenceId": "2", "SentenceText": "Performans primi olarak da\u011f\u0131t\u0131lan yay\u0131n gelirleri kul\u00fcplerin kasas\u0131n\u0131 doldurdu .", "Tokens": [{"Token": "Performans", "EventTrigger": "O", "EventArgument": "O"}, {"Token": "primi", "EventTrigger": "O", "EventArgument": "O"}, {"Token": "olarak", "EventTrigger": "O", "EventArgument": "O"}, {"Token": "da\u011f\u0131t\u0131lan", "EventTrigger": "O", "EventArgument": "O"}, {"Token": "yay\u0131n", "EventTrigger": "O", "EventArgument": "O"}, {"Token": "gelirleri", "EventTrigger": "Gelir-Duyuru", "EventArgument": "O"}, {"Token": "kul\u00fcplerin", "EventTrigger": "O", "EventArgument": "O"}, {"Token": "kasas\u0131n\u0131", "EventTrigger": "O", "EventArgument": "O"}, {"Token": "doldurdu", "EventTrigger": "O", "EventArgument": "O"}, {"Token": ".", "EventTrigger": "O", "EventArgument": "O"}]}, {"SentenceId": "3", "SentenceText": "2010-2011 sezonunun ilk devresinde 18 tak\u0131m 122 milyon lira prim ald\u0131 .", "Tokens": [{"Token": "2010-2011", "EventTrigger": "O", "EventArgument": "O"}, {"Token": "sezonunun", "EventTrigger": "O", "EventArgument": "O"}, {"Token": "ilk", "EventTrigger": "O", "EventArgument": "O"}, {"Token": "devresinde", "EventTrigger": "O", "EventArgument": "O"}, {"Token": "18", "EventTrigger": "O", "EventArgument": "O"}, {"Token": "tak\u0131m", "EventTrigger": "O", "EventArgument": "O"}, {"Token": "122", "EventTrigger": "O", "EventArgument": "O"}, {"Token": "milyon", "EventTrigger": "O", "EventArgument": "O"}, {"Token": "lira", "EventTrigger": "O", "EventArgument": "O"}, {"Token": "prim", "EventTrigger": "O", "EventArgument": "O"}, {"Token": "ald\u0131", "EventTrigger": "O", "EventArgument": "O"}, {"Token": ".", "EventTrigger": "O", "EventArgument": "O"}]}, {"SentenceId": "4", "SentenceText": "Bu tak\u0131mlar aras\u0131nda en fazla paray\u0131 lider Trabzonspor kazan\u0131rken , bordo-mavili ekip kasas\u0131na haftada 639 bin lira para koydu .", "Tokens": [{"Token": "Bu", "EventTrigger": "O", "EventArgument": "O"}, {"Token": "tak\u0131mlar", "EventTrigger": "O", "EventArgument": "O"}, {"Token": "aras\u0131nda", "EventTrigger": "O", "EventArgument": "O"}, {"Token": "en", "EventTrigger": "O", "EventArgument": "O"}, {"Token": "fazla", "EventTrigger": "O", "EventArgument": "O"}, {"Token": "paray\u0131", "EventTrigger": "O", "EventArgument": "O"}, {"Token": "lider", "EventTrigger": "O", "EventArgument": "O"}, {"Token": "Trabzonspor", "EventTrigger": "O", "EventArgument": "O"}, {"Token": "kazan\u0131rken", "EventTrigger": "O", "EventArgument": "O"}, {"Token": ",", "EventTrigger": "O", "EventArgument": "O"}, {"Token": "bordo-mavili", "EventTrigger": "O", "EventArgument": "O"}, {"Token": "ekip", "EventTrigger": "O", "EventArgument": "O"}, {"Token": "kasas\u0131na", "EventTrigger": "O", "EventArgument": "O"}, {"Token": "haftada", "EventTrigger": "O", "EventArgument": "O"}, {"Token": "639", "EventTrigger": "O", "EventArgument": "O"}, {"Token": "bin", "EventTrigger": "O", "EventArgument": "O"}, {"Token": "lira", "EventTrigger": "O", "EventArgument": "O"}, {"Token": "para", "EventTrigger": "O", "EventArgument": "O"}, {"Token": "koydu", "EventTrigger": "O", "EventArgument": "O"}, {"Token": ".", "EventTrigger": "O", "EventArgument": "O"}]}, {"SentenceId": "5", "SentenceText": "SPOR Toto S\u00fcper Lig \u2019 in ilk yar\u0131s\u0131nda 18 kul\u00fcp 122 milyon lira para kazand\u0131 .", "Tokens": [{"Token": "SPOR", "EventTrigger": "O", "EventArgument": "O"}, {"Token": "Toto", "EventTrigger": "O", "EventArgument": "O"}, {"Token": "S\u00fcper", "EventTrigger": "O", "EventArgument": "O"}, {"Token": "Lig", "EventTrigger": "O", "EventArgument": "O"}, {"Token": "\u2019", "EventTrigger": "O", "EventArgument": "O"}, {"Token": "in", "EventTrigger": "O", "EventArgument": "O"}, {"Token": "ilk", "EventTrigger": "O", "EventArgument": "O"}, {"Token": "yar\u0131s\u0131nda", "EventTrigger": "O", "EventArgument": "O"}, {"Token": "18", "EventTrigger": "O", "EventArgument": "O"}, {"Token": "kul\u00fcp", "EventTrigger": "O", "EventArgument": "O"}, {"Token": "122", "EventTrigger": "O", "EventArgument": "O"}, {"Token": "milyon", "EventTrigger": "O", "EventArgument": "O"}, {"Token": "lira", "EventTrigger": "O", "EventArgument": "O"}, {"Token": "para", "EventTrigger": "O", "EventArgument": "O"}, {"Token": "kazand\u0131", "EventTrigger": "O", "EventArgument": "O"}, {"Token": ".", "EventTrigger": "O", "EventArgument": "O"}]}, {"SentenceId": "6", "SentenceText": "Performans primi olarak da\u011f\u0131t\u0131lan yay\u0131n gelirlerinden haftada 7.2 milyon lira kazanan 18 tak\u0131m aras\u0131nda en \u00e7ok paray\u0131 Trabzonspor ald\u0131 .", "Tokens": [{"Token": "Performans", "EventTrigger": "O", "EventArgument": "O"}, {"Token": "primi", "EventTrigger": "O", "EventArgument": "O"}, {"Token": "olarak", "EventTrigger": "O", "EventArgument": "O"}, {"Token": "da\u011f\u0131t\u0131lan", "EventTrigger": "O", "EventArgument": "O"}, {"Token": "yay\u0131n", "EventTrigger": "O", "EventArgument": "O"}, {"Token": "gelirlerinden", "EventTrigger": "Gelir-Duyuru", "EventArgument": "O"}, {"Token": "haftada", "EventTrigger": "O", "EventArgument": "B-ZAMAN"}, {"Token": "7.2", "EventTrigger": "O", "EventArgument": "B-PARA"}, {"Token": "milyon", "EventTrigger": "O", "EventArgument": "I-PARA"}, {"Token": "lira", "EventTrigger": "O", "EventArgument": "I-PARA"}, {"Token": "kazanan", "EventTrigger": "O", "EventArgument": "O"}, {"Token": "18", "EventTrigger": "O", "EventArgument": "O"}, {"Token": "tak\u0131m", "EventTrigger": "O", "EventArgument": "O"}, {"Token": "aras\u0131nda", "EventTrigger": "O", "EventArgument": "O"}, {"Token": "en", "EventTrigger": "O", "EventArgument": "O"}, {"Token": "\u00e7ok", "EventTrigger": "O", "EventArgument": "O"}, {"Token": "paray\u0131", "EventTrigger": "O", "EventArgument": "O"}, {"Token": "Trabzonspor", "EventTrigger": "O", "EventArgument": "B-\u015e\u0130RKET"}, {"Token": "ald\u0131", "EventTrigger": "O", "EventArgument": "O"}, {"Token": ".", "EventTrigger": "O", "EventArgument": "O"}]}, {"SentenceId": "7", "SentenceText": "Sezonun ilk devresinde 10 milyon 875 bin lirayla gelir liginde ilk sar\u0131da yer alan bordo-mavili ekip haftada ortalama 639 bin lira para kazand\u0131 .", "Tokens": [{"Token": "Sezonun", "EventTrigger": "O", "EventArgument": "O"}, {"Token": "ilk", "EventTrigger": "O", "EventArgument": "O"}, {"Token": "devresinde", "EventTrigger": "O", "EventArgument": "O"}, {"Token": "10", "EventTrigger": "O", "EventArgument": "B-PARA"}, {"Token": "milyon", "EventTrigger": "O", "EventArgument": "I-PARA"}, {"Token": "875", "EventTrigger": "O", "EventArgument": "I-PARA"}, {"Token": "bin", "EventTrigger": "O", "EventArgument": "I-PARA"}, {"Token": "lirayla", "EventTrigger": "O", "EventArgument": "I-PARA"}, {"Token": "gelir", "EventTrigger": "Gelir-Duyuru", "EventArgument": "O"}, {"Token": "liginde", "EventTrigger": "O", "EventArgument": "O"}, {"Token": "ilk", "EventTrigger": "O", "EventArgument": "O"}, {"Token": "sar\u0131da", "EventTrigger": "O", "EventArgument": "O"}, {"Token": "yer", "EventTrigger": "O", "EventArgument": "O"}, {"Token": "alan", "EventTrigger": "O", "EventArgument": "O"}, {"Token": "bordo-mavili", "EventTrigger": "O", "EventArgument": "O"}, {"Token": "ekip", "EventTrigger": "O", "EventArgument": "O"}, {"Token": "haftada", "EventTrigger": "O", "EventArgument": "O"}, {"Token": "ortalama", "EventTrigger": "O", "EventArgument": "O"}, {"Token": "639", "EventTrigger": "O", "EventArgument": "O"}, {"Token": "bin", "EventTrigger": "O", "EventArgument": "O"}, {"Token": "lira", "EventTrigger": "O", "EventArgument": "O"}, {"Token": "para", "EventTrigger": "O", "EventArgument": "O"}, {"Token": "kazand\u0131", "EventTrigger": "O", "EventArgument": "O"}, {"Token": ".", "EventTrigger": "O", "EventArgument": "O"}]}, {"SentenceId": "8", "SentenceText": "En az kazanan tak\u0131m ise 2.6 milyon liral\u0131k geliriyle Kas\u0131mpa\u015faspor oldu .", "Tokens": [{"Token": "En", "EventTrigger": "O", "EventArgument": "O"}, {"Token": "az", "EventTrigger": "O", "EventArgument": "O"}, {"Token": "kazanan", "EventTrigger": "O", "EventArgument": "O"}, {"Token": "tak\u0131m", "EventTrigger": "O", "EventArgument": "O"}, {"Token": "ise", "EventTrigger": "O", "EventArgument": "O"}, {"Token": "2.6", "EventTrigger": "O", "EventArgument": "B-PARA"}, {"Token": "milyon", "EventTrigger": "O", "EventArgument": "I-PARA"}, {"Token": "liral\u0131k", "EventTrigger": "O", "EventArgument": "I-PARA"}, {"Token": "geliriyle", "EventTrigger": "Gelir-Duyuru", "EventArgument": "O"}, {"Token": "Kas\u0131mpa\u015faspor", "EventTrigger": "O", "EventArgument": "B-\u015e\u0130RKET"}, {"Token": "oldu", "EventTrigger": "O", "EventArgument": "O"}, {"Token": ".", "EventTrigger": "O", "EventArgument": "O"}]}, {"SentenceId": "9", "SentenceText": "Ligde 5 tak\u0131m\u0131 bulunan \u0130stanbul ise en \u00e7ok kazanan il oldu .", "Tokens": [{"Token": "Ligde", "EventTrigger": "O", "EventArgument": "O"}, {"Token": "5", "EventTrigger": "O", "EventArgument": "O"}, {"Token": "tak\u0131m\u0131", "EventTrigger": "O", "EventArgument": "O"}, {"Token": "bulunan", "EventTrigger": "O", "EventArgument": "O"}, {"Token": "\u0130stanbul", "EventTrigger": "O", "EventArgument": "O"}, {"Token": "ise", "EventTrigger": "O", "EventArgument": "O"}, {"Token": "en", "EventTrigger": "O", "EventArgument": "O"}, {"Token": "\u00e7ok", "EventTrigger": "O", "EventArgument": "O"}, {"Token": "kazanan", "EventTrigger": "O", "EventArgument": "O"}, {"Token": "il", "EventTrigger": "O", "EventArgument": "O"}, {"Token": "oldu", "EventTrigger": "O", "EventArgument": "O"}, {"Token": ".", "EventTrigger": "O", "EventArgument": "O"}]}, {"SentenceId": "10", "SentenceText": "5 kul\u00fcb\u00fcn geliri 30 milyon liray\u0131 a\u015ft\u0131 .", "Tokens": [{"Token": "5", "EventTrigger": "O", "EventArgument": "O"}, {"Token": "kul\u00fcb\u00fcn", "EventTrigger": "O", "EventArgument": "O"}, {"Token": "geliri", "EventTrigger": "Gelir-Art\u0131\u015f", "EventArgument": "O"}, {"Token": "30", "EventTrigger": "O", "EventArgument": "B-PARA"}, {"Token": "milyon", "EventTrigger": "O", "EventArgument": "I-PARA"}, {"Token": "liray\u0131", "EventTrigger": "O", "EventArgument": "I-PARA"}, {"Token": "a\u015ft\u0131", "EventTrigger": "Gelir-Art\u0131\u015f", "EventArgument": "O"}, {"Token": ".", "EventTrigger": "O", "EventArgument": "O"}]}, {"SentenceId": "11", "SentenceText": "9.7 milyonluk galibiyet Ligin en \u00e7ok kazanan tak\u0131m\u0131 Trabzonspor 17 haftada 10 milyon 875 bin TL \u2019 lik gelire ula\u015ft\u0131 .", "Tokens": [{"Token": "9.7", "EventTrigger": "O", "EventArgument": "B-PARA"}, {"Token": "milyonluk", "EventTrigger": "O", "EventArgument": "I-PARA"}, {"Token": "galibiyet", "EventTrigger": "O", "EventArgument": "O"}, {"Token": "Ligin", "EventTrigger": "O", "EventArgument": "O"}, {"Token": "en", "EventTrigger": "O", "EventArgument": "O"}, {"Token": "\u00e7ok", "EventTrigger": "O", "EventArgument": "O"}, {"Token": "kazanan", "EventTrigger": "O", "EventArgument": "O"}, {"Token": "tak\u0131m\u0131", "EventTrigger": "O", "EventArgument": "O"}, {"Token": "Trabzonspor", "EventTrigger": "O", "EventArgument": "B-\u015e\u0130RKET"}, {"Token": "17", "EventTrigger": "O", "EventArgument": "B-ZAMAN"}, {"Token": "haftada", "EventTrigger": "O", "EventArgument": "I-ZAMAN"}, {"Token": "10", "EventTrigger": "O", "EventArgument": "B-PARA"}, {"Token": "milyon", "EventTrigger": "O", "EventArgument": "I-PARA"}, {"Token": "875", "EventTrigger": "O", "EventArgument": "I-PARA"}, {"Token": "bin", "EventTrigger": "O", "EventArgument": "I-PARA"}, {"Token": "TL", "EventTrigger": "O", "EventArgument": "I-PARA"}, {"Token": "\u2019", "EventTrigger": "O", "EventArgument": "O"}, {"Token": "lik", "EventTrigger": "O", "EventArgument": "O"}, {"Token": "gelire", "EventTrigger": "Gelir-Art\u0131\u015f", "EventArgument": "O"}, {"Token": "ula\u015ft\u0131", "EventTrigger": "Gelir-Art\u0131\u015f", "EventArgument": "O"}, {"Token": ".", "EventTrigger": "O", "EventArgument": "O"}]}, {"SentenceId": "12", "SentenceText": "Bordo-mavili ekip 13 galibiyetle 9 milyon 750 bin TL \u2019 lik performans primi almay\u0131 ba\u015fard\u0131 .", "Tokens": [{"Token": "Bordo-mavili", "EventTrigger": "O", "EventArgument": "O"}, {"Token": "ekip", "EventTrigger": "O", "EventArgument": "O"}, {"Token": "13", "EventTrigger": "O", "EventArgument": "O"}, {"Token": "galibiyetle", "EventTrigger": "O", "EventArgument": "O"}, {"Token": "9", "EventTrigger": "O", "EventArgument": "O"}, {"Token": "milyon", "EventTrigger": "O", "EventArgument": "O"}, {"Token": "750", "EventTrigger": "O", "EventArgument": "O"}, {"Token": "bin", "EventTrigger": "O", "EventArgument": "O"}, {"Token": "TL", "EventTrigger": "O", "EventArgument": "O"}, {"Token": "\u2019", "EventTrigger": "O", "EventArgument": "O"}, {"Token": "lik", "EventTrigger": "O", "EventArgument": "O"}, {"Token": "performans", "EventTrigger": "O", "EventArgument": "O"}, {"Token": "primi", "EventTrigger": "O", "EventArgument": "O"}, {"Token": "almay\u0131", "EventTrigger": "O", "EventArgument": "O"}, {"Token": "ba\u015fard\u0131", "EventTrigger": "O", "EventArgument": "O"}, {"Token": ".", "EventTrigger": "O", "EventArgument": "O"}]}, {"SentenceId": "13", "SentenceText": "Ligde oynad\u0131\u011f\u0131 17 ma\u00e7ta 3 kar\u015f\u0131la\u015fmadan berabere ayr\u0131lan Trabzonspor kasas\u0131na 1 milyon 125 bin lira para koydu .", "Tokens": [{"Token": "Ligde", "EventTrigger": "O", "EventArgument": "O"}, {"Token": "oynad\u0131\u011f\u0131", "EventTrigger": "O", "EventArgument": "O"}, {"Token": "17", "EventTrigger": "O", "EventArgument": "O"}, {"Token": "ma\u00e7ta", "EventTrigger": "O", "EventArgument": "O"}, {"Token": "3", "EventTrigger": "O", "EventArgument": "O"}, {"Token": "kar\u015f\u0131la\u015fmadan", "EventTrigger": "O", "EventArgument": "O"}, {"Token": "berabere", "EventTrigger": "O", "EventArgument": "O"}, {"Token": "ayr\u0131lan", "EventTrigger": "O", "EventArgument": "O"}, {"Token": "Trabzonspor", "EventTrigger": "O", "EventArgument": "O"}, {"Token": "kasas\u0131na", "EventTrigger": "O", "EventArgument": "O"}, {"Token": "1", "EventTrigger": "O", "EventArgument": "O"}, {"Token": "milyon", "EventTrigger": "O", "EventArgument": "O"}, {"Token": "125", "EventTrigger": "O", "EventArgument": "O"}, {"Token": "bin", "EventTrigger": "O", "EventArgument": "O"}, {"Token": "lira", "EventTrigger": "O", "EventArgument": "O"}, {"Token": "para", "EventTrigger": "O", "EventArgument": "O"}, {"Token": "koydu", "EventTrigger": "O", "EventArgument": "O"}, {"Token": ".", "EventTrigger": "O", "EventArgument": "O"}]}, {"SentenceId": "14", "SentenceText": "Haftada ortalama 632 bin TL kazanan bordo-mavililer bilet geliriyle de kasas\u0131n\u0131 doldurdu .", "Tokens": [{"Token": "Haftada", "EventTrigger": "O", "EventArgument": "O"}, {"Token": "ortalama", "EventTrigger": "O", "EventArgument": "O"}, {"Token": "632", "EventTrigger": "O", "EventArgument": "B-PARA"}, {"Token": "bin", "EventTrigger": "O", "EventArgument": "I-PARA"}, {"Token": "TL", "EventTrigger": "O", "EventArgument": "I-PARA"}, {"Token": "kazanan", "EventTrigger": "O", "EventArgument": "O"}, {"Token": "bordo-mavililer", "EventTrigger": "O", "EventArgument": "O"}, {"Token": "bilet", "EventTrigger": "O", "EventArgument": "O"}, {"Token": "geliriyle", "EventTrigger": "Gelir-Duyuru", "EventArgument": "O"}, {"Token": "de", "EventTrigger": "O", "EventArgument": "O"}, {"Token": "kasas\u0131n\u0131", "EventTrigger": "O", "EventArgument": "O"}, {"Token": "doldurdu", "EventTrigger": "O", "EventArgument": "O"}, {"Token": ".", "EventTrigger": "O", "EventArgument": "O"}]}, {"SentenceId": "15", "SentenceText": "\u0130lk yar\u0131da S\u00fcper Lig \u2019 e damga vuran Trabzonspor Ziraat T\u00fcrkiye Kupas\u0131 \u2019 yla da geliri art\u0131rmaya \u00e7al\u0131\u015f\u0131yor .", "Tokens": [{"Token": "\u0130lk", "EventTrigger": "O", "EventArgument": "O"}, {"Token": "yar\u0131da", "EventTrigger": "O", "EventArgument": "O"}, {"Token": "S\u00fcper", "EventTrigger": "O", "EventArgument": "O"}, {"Token": "Lig", "EventTrigger": "O", "EventArgument": "O"}, {"Token": "\u2019", "EventTrigger": "O", "EventArgument": "O"}, {"Token": "e", "EventTrigger": "O", "EventArgument": "O"}, {"Token": "damga", "EventTrigger": "O", "EventArgument": "O"}, {"Token": "vuran", "EventTrigger": "O", "EventArgument": "O"}, {"Token": "Trabzonspor", "EventTrigger": "O", "EventArgument": "B-\u015e\u0130RKET"}, {"Token": "Ziraat", "EventTrigger": "O", "EventArgument": "O"}, {"Token": "T\u00fcrkiye", "EventTrigger": "O", "EventArgument": "O"}, {"Token": "Kupas\u0131", "EventTrigger": "O", "EventArgument": "O"}, {"Token": "\u2019", "EventTrigger": "O", "EventArgument": "O"}, {"Token": "yla", "EventTrigger": "O", "EventArgument": "O"}, {"Token": "da", "EventTrigger": "O", "EventArgument": "O"}, {"Token": "geliri", "EventTrigger": "Gelir-Art\u0131\u015f", "EventArgument": "O"}, {"Token": "art\u0131rmaya", "EventTrigger": "Gelir-Art\u0131\u015f", "EventArgument": "O"}, {"Token": "\u00e7al\u0131\u015f\u0131yor", "EventTrigger": "O", "EventArgument": "O"}, {"Token": ".", "EventTrigger": "O", "EventArgument": "O"}]}, {"SentenceId": "16", "SentenceText": "Gelirde 2 \u2019 nci Bursaspor S\u00fcper Lig \u2019 in son \u015fampiyonu Bursaspor \u2019 da bu sezon gelirini art\u0131rmaya devam ediyor .", "Tokens": [{"Token": "Gelirde", "EventTrigger": "Gelir-Duyuru", "EventArgument": "O"}, {"Token": "2", "EventTrigger": "O", "EventArgument": "O"}, {"Token": "\u2019", "EventTrigger": "O", "EventArgument": "O"}, {"Token": "nci", "EventTrigger": "O", "EventArgument": "O"}, {"Token": "Bursaspor", "EventTrigger": "O", "EventArgument": "O"}, {"Token": "S\u00fcper", "EventTrigger": "O", "EventArgument": "O"}, {"Token": "Lig", "EventTrigger": "O", "EventArgument": "O"}, {"Token": "\u2019", "EventTrigger": "O", "EventArgument": "O"}, {"Token": "in", "EventTrigger": "O", "EventArgument": "O"}, {"Token": "son", "EventTrigger": "O", "EventArgument": "O"}, {"Token": "\u015fampiyonu", "EventTrigger": "O", "EventArgument": "O"}, {"Token": "Bursaspor", "EventTrigger": "O", "EventArgument": "B-\u015e\u0130RKET"}, {"Token": "\u2019", "EventTrigger": "O", "EventArgument": "O"}, {"Token": "da", "EventTrigger": "O", "EventArgument": "O"}, {"Token": "bu", "EventTrigger": "O", "EventArgument": "B-ZAMAN"}, {"Token": "sezon", "EventTrigger": "O", "EventArgument": "I-ZAMAN"}, {"Token": "gelirini", "EventTrigger": "Gelir-Art\u0131\u015f", "EventArgument": "O"}, {"Token": "art\u0131rmaya", "EventTrigger": "Gelir-Art\u0131\u015f", "EventArgument": "O"}, {"Token": "devam", "EventTrigger": "O", "EventArgument": "O"}, {"Token": "ediyor", "EventTrigger": "O", "EventArgument": "O"}, {"Token": ".", "EventTrigger": "O", "EventArgument": "O"}]}, {"SentenceId": "17", "SentenceText": "2009-2010 sezonunda kasas\u0131na 60 milyon liradan fazla para koyan Bursaspor bu sezon \u015eampiyonlar Ligi \u2019 yle kazanc\u0131n\u0131 art\u0131rd\u0131 .", "Tokens": [{"Token": "2009-2010", "EventTrigger": "O", "EventArgument": "O"}, {"Token": "sezonunda", "EventTrigger": "O", "EventArgument": "O"}, {"Token": "kasas\u0131na", "EventTrigger": "O", "EventArgument": "O"}, {"Token": "60", "EventTrigger": "O", "EventArgument": "O"}, {"Token": "milyon", "EventTrigger": "O", "EventArgument": "O"}, {"Token": "liradan", "EventTrigger": "O", "EventArgument": "O"}, {"Token": "fazla", "EventTrigger": "O", "EventArgument": "O"}, {"Token": "para", "EventTrigger": "O", "EventArgument": "O"}, {"Token": "koyan", "EventTrigger": "O", "EventArgument": "O"}, {"Token": "Bursaspor", "EventTrigger": "O", "EventArgument": "O"}, {"Token": "bu", "EventTrigger": "O", "EventArgument": "O"}, {"Token": "sezon", "EventTrigger": "O", "EventArgument": "O"}, {"Token": "\u015eampiyonlar", "EventTrigger": "O", "EventArgument": "O"}, {"Token": "Ligi", "EventTrigger": "O", "EventArgument": "O"}, {"Token": "\u2019", "EventTrigger": "O", "EventArgument": "O"}, {"Token": "yle", "EventTrigger": "O", "EventArgument": "O"}, {"Token": "kazanc\u0131n\u0131", "EventTrigger": "Gelir-Art\u0131\u015f", "EventArgument": "O"}, {"Token": "art\u0131rd\u0131", "EventTrigger": "Gelir-Art\u0131\u015f", "EventArgument": "O"}, {"Token": ".", "EventTrigger": "O", "EventArgument": "O"}]}, {"SentenceId": "18", "SentenceText": "Spor Toto S\u00fcper Lig \u2019 de toplad\u0131\u011f\u0131 puanlarla 2 \u2019 ncilik koltu\u011funa oturan Bursaspor , 17 haftada 9.7 milyon lira performans primi ald\u0131 .", "Tokens": [{"Token": "Spor", "EventTrigger": "O", "EventArgument": "O"}, {"Token": "Toto", "EventTrigger": "O", "EventArgument": "O"}, {"Token": "S\u00fcper", "EventTrigger": "O", "EventArgument": "O"}, {"Token": "Lig", "EventTrigger": "O", "EventArgument": "O"}, {"Token": "\u2019", "EventTrigger": "O", "EventArgument": "O"}, {"Token": "de", "EventTrigger": "O", "EventArgument": "O"}, {"Token": "toplad\u0131\u011f\u0131", "EventTrigger": "O", "EventArgument": "O"}, {"Token": "puanlarla", "EventTrigger": "O", "EventArgument": "O"}, {"Token": "2", "EventTrigger": "O", "EventArgument": "O"}, {"Token": "\u2019", "EventTrigger": "O", "EventArgument": "O"}, {"Token": "ncilik", "EventTrigger": "O", "EventArgument": "O"}, {"Token": "koltu\u011funa", "EventTrigger": "O", "EventArgument": "O"}, {"Token": "oturan", "EventTrigger": "O", "EventArgument": "O"}, {"Token": "Bursaspor", "EventTrigger": "O", "EventArgument": "O"}, {"Token": ",", "EventTrigger": "O", "EventArgument": "O"}, {"Token": "17", "EventTrigger": "O", "EventArgument": "O"}, {"Token": "haftada", "EventTrigger": "O", "EventArgument": "O"}, {"Token": "9.7", "EventTrigger": "O", "EventArgument": "O"}, {"Token": "milyon", "EventTrigger": "O", "EventArgument": "O"}, {"Token": "lira", "EventTrigger": "O", "EventArgument": "O"}, {"Token": "performans", "EventTrigger": "O", "EventArgument": "O"}, {"Token": "primi", "EventTrigger": "O", "EventArgument": "O"}, {"Token": "ald\u0131", "EventTrigger": "O", "EventArgument": "O"}, {"Token": ".", "EventTrigger": "O", "EventArgument": "O"}]}, {"SentenceId": "19", "SentenceText": "11 galibiyetle 8 milyon 250 bin TL \u2019 lik \u00f6d\u00fcl\u00fc kasas\u0131na koyan ye\u015fil-beyazl\u0131 ekip , 4 beraberlikten de 1.5 milyon liral\u0131k \u00f6d\u00fcl ald\u0131 .", "Tokens": [{"Token": "11", "EventTrigger": "O", "EventArgument": "O"}, {"Token": "galibiyetle", "EventTrigger": "O", "EventArgument": "O"}, {"Token": "8", "EventTrigger": "O", "EventArgument": "O"}, {"Token": "milyon", "EventTrigger": "O", "EventArgument": "O"}, {"Token": "250", "EventTrigger": "O", "EventArgument": "I-PARA"}, {"Token": "bin", "EventTrigger": "O", "EventArgument": "I-PARA"}, {"Token": "TL", "EventTrigger": "O", "EventArgument": "I-PARA"}, {"Token": "\u2019", "EventTrigger": "O", "EventArgument": "O"}, {"Token": "lik", "EventTrigger": "O", "EventArgument": "O"}, {"Token": "\u00f6d\u00fcl\u00fc", "EventTrigger": "Marka-\u00d6d\u00fcl", "EventArgument": "O"}, {"Token": "kasas\u0131na", "EventTrigger": "O", "EventArgument": "O"}, {"Token": "koyan", "EventTrigger": "O", "EventArgument": "O"}, {"Token": "ye\u015fil-beyazl\u0131", "EventTrigger": "O", "EventArgument": "O"}, {"Token": "ekip", "EventTrigger": "O", "EventArgument": "O"}, {"Token": ",", "EventTrigger": "O", "EventArgument": "O"}, {"Token": "4", "EventTrigger": "O", "EventArgument": "O"}, {"Token": "beraberlikten", "EventTrigger": "O", "EventArgument": "O"}, {"Token": "de", "EventTrigger": "O", "EventArgument": "O"}, {"Token": "1.5", "EventTrigger": "O", "EventArgument": "O"}, {"Token": "milyon", "EventTrigger": "O", "EventArgument": "I-PARA"}, {"Token": "liral\u0131k", "EventTrigger": "O", "EventArgument": "I-PARA"}, {"Token": "\u00f6d\u00fcl", "EventTrigger": "Marka-\u00d6d\u00fcl", "EventArgument": "O"}, {"Token": "ald\u0131", "EventTrigger": "O", "EventArgument": "O"}, {"Token": ".", "EventTrigger": "O", "EventArgument": "O"}]}, {"SentenceId": "20", "SentenceText": "Bursaspor \u2019 un \u015eampiyonlar Ligi \u2019 nden ise 20 milyon liradan fazla kazanmas\u0131 bekleniyor .", "Tokens": [{"Token": "Bursaspor", "EventTrigger": "O", "EventArgument": "O"}, {"Token": "\u2019", "EventTrigger": "O", "EventArgument": "O"}, {"Token": "un", "EventTrigger": "O", "EventArgument": "O"}, {"Token": "\u015eampiyonlar", "EventTrigger": "O", "EventArgument": "O"}, {"Token": "Ligi", "EventTrigger": "O", "EventArgument": "O"}, {"Token": "\u2019", "EventTrigger": "O", "EventArgument": "O"}, {"Token": "nden", "EventTrigger": "O", "EventArgument": "O"}, {"Token": "ise", "EventTrigger": "O", "EventArgument": "O"}, {"Token": "20", "EventTrigger": "O", "EventArgument": "O"}, {"Token": "milyon", "EventTrigger": "O", "EventArgument": "O"}, {"Token": "liradan", "EventTrigger": "O", "EventArgument": "O"}, {"Token": "fazla", "EventTrigger": "O", "EventArgument": "O"}, {"Token": "kazanmas\u0131", "EventTrigger": "O", "EventArgument": "O"}, {"Token": "bekleniyor", "EventTrigger": "O", "EventArgument": "O"}, {"Token": ".", "EventTrigger": "O", "EventArgument": "O"}]}, {"SentenceId": "21", "SentenceText": "3 b\u00fcy\u00fck 22 milyon ald\u0131 Yeni projelerle gelirini art\u0131rmaya \u00e7al\u0131\u015fan 3 b\u00fcy\u00fck kul\u00fcp ise performans priminde istenilen ba\u015far\u0131y\u0131 yakalayamad\u0131 .", "Tokens": [{"Token": "3", "EventTrigger": "O", "EventArgument": "O"}, {"Token": "b\u00fcy\u00fck", "EventTrigger": "O", "EventArgument": "O"}, {"Token": "22", "EventTrigger": "O", "EventArgument": "B-PARA"}, {"Token": "milyon", "EventTrigger": "O", "EventArgument": "I-PARA"}, {"Token": "ald\u0131", "EventTrigger": "O", "EventArgument": "O"}, {"Token": "Yeni", "EventTrigger": "O", "EventArgument": "O"}, {"Token": "projelerle", "EventTrigger": "Proje", "EventArgument": "O"}, {"Token": "gelirini", "EventTrigger": "Gelir-Art\u0131\u015f", "EventArgument": "O"}, {"Token": "art\u0131rmaya", "EventTrigger": "Gelir-Art\u0131\u015f", "EventArgument": "O"}, {"Token": "\u00e7al\u0131\u015fan", "EventTrigger": "O", "EventArgument": "O"}, {"Token": "3", "EventTrigger": "O", "EventArgument": "O"}, {"Token": "b\u00fcy\u00fck", "EventTrigger": "O", "EventArgument": "O"}, {"Token": "kul\u00fcp", "EventTrigger": "O", "EventArgument": "O"}, {"Token": "ise", "EventTrigger": "O", "EventArgument": "O"}, {"Token": "performans", "EventTrigger": "O", "EventArgument": "O"}, {"Token": "priminde", "EventTrigger": "O", "EventArgument": "O"}, {"Token": "istenilen", "EventTrigger": "O", "EventArgument": "O"}, {"Token": "ba\u015far\u0131y\u0131", "EventTrigger": "O", "EventArgument": "O"}, {"Token": "yakalayamad\u0131", "EventTrigger": "O", "EventArgument": "O"}, {"Token": ".", "EventTrigger": "O", "EventArgument": "O"}]}, {"SentenceId": "22", "SentenceText": "Bu sezonun ilk yar\u0131s\u0131nda Fenerbah\u00e7e , Be\u015fikta\u015f ve Galatasaray \u2019 \u0131n performans geliri 22 milyon lirada kald\u0131 .", "Tokens": [{"Token": "Bu", "EventTrigger": "O", "EventArgument": "B-ZAMAN"}, {"Token": "sezonun", "EventTrigger": "O", "EventArgument": "I-ZAMAN"}, {"Token": "ilk", "EventTrigger": "O", "EventArgument": "I-ZAMAN"}, {"Token": "yar\u0131s\u0131nda", "EventTrigger": "O", "EventArgument": "I-ZAMAN"}, {"Token": "Fenerbah\u00e7e", "EventTrigger": "O", "EventArgument": "B-\u015e\u0130RKET"}, {"Token": ",", "EventTrigger": "O", "EventArgument": "O"}, {"Token": "Be\u015fikta\u015f", "EventTrigger": "O", "EventArgument": "B-\u015e\u0130RKET"}, {"Token": "ve", "EventTrigger": "O", "EventArgument": "O"}, {"Token": "Galatasaray", "EventTrigger": "O", "EventArgument": "B-\u015e\u0130RKET"}, {"Token": "\u2019", "EventTrigger": "O", "EventArgument": "O"}, {"Token": "\u0131n", "EventTrigger": "O", "EventArgument": "O"}, {"Token": "performans", "EventTrigger": "O", "EventArgument": "O"}, {"Token": "geliri", "EventTrigger": "Gelir-Duyuru", "EventArgument": "O"}, {"Token": "22", "EventTrigger": "O", "EventArgument": "B-PARA"}, {"Token": "milyon", "EventTrigger": "O", "EventArgument": "I-PARA"}, {"Token": "lirada", "EventTrigger": "O", "EventArgument": "I-PARA"}, {"Token": "kald\u0131", "EventTrigger": "O", "EventArgument": "O"}, {"Token": ".", "EventTrigger": "O", "EventArgument": "O"}]}, {"SentenceId": "23", "SentenceText": "3 b\u00fcy\u00fckler aras\u0131nda en fazla paray\u0131 Fenerbah\u00e7e kazan\u0131rken Galatasaray 6 milyon lira yay\u0131n geliri alabildi .", "Tokens": [{"Token": "3", "EventTrigger": "O", "EventArgument": "O"}, {"Token": "b\u00fcy\u00fckler", "EventTrigger": "O", "EventArgument": "O"}, {"Token": "aras\u0131nda", "EventTrigger": "O", "EventArgument": "O"}, {"Token": "en", "EventTrigger": "O", "EventArgument": "O"}, {"Token": "fazla", "EventTrigger": "O", "EventArgument": "O"}, {"Token": "paray\u0131", "EventTrigger": "O", "EventArgument": "O"}, {"Token": "Fenerbah\u00e7e", "EventTrigger": "O", "EventArgument": "B-\u015e\u0130RKET"}, {"Token": "kazan\u0131rken", "EventTrigger": "O", "EventArgument": "O"}, {"Token": "Galatasaray", "EventTrigger": "O", "EventArgument": "B-\u015e\u0130RKET"}, {"Token": "6", "EventTrigger": "O", "EventArgument": "B-PARA"}, {"Token": "milyon", "EventTrigger": "O", "EventArgument": "I-PARA"}, {"Token": "lira", "EventTrigger": "O", "EventArgument": "I-PARA"}, {"Token": "yay\u0131n", "EventTrigger": "O", "EventArgument": "O"}, {"Token": "geliri", "EventTrigger": "Gelir-Duyuru", "EventArgument": "O"}, {"Token": "alabildi", "EventTrigger": "O", "EventArgument": "O"}, {"Token": ".", "EventTrigger": "O", "EventArgument": "O"}]}, {"SentenceId": "24", "SentenceText": "Fla\u015f transferlerle forma sat\u0131\u015f\u0131n\u0131 art\u0131ran Be\u015fikta\u015f \u2019 \u0131n geliri ise 7.5 milyon lirada kald\u0131 .", "Tokens": [{"Token": "Fla\u015f", "EventTrigger": "O", "EventArgument": "O"}, {"Token": "transferlerle", "EventTrigger": "O", "EventArgument": "O"}, {"Token": "forma", "EventTrigger": "O", "EventArgument": "O"}, {"Token": "sat\u0131\u015f\u0131n\u0131", "EventTrigger": "\u00dcr\u00fcn-Satma", "EventArgument": "O"}, {"Token": "art\u0131ran", "EventTrigger": "O", "EventArgument": "O"}, {"Token": "Be\u015fikta\u015f", "EventTrigger": "O", "EventArgument": "B-\u015e\u0130RKET"}, {"Token": "\u2019", "EventTrigger": "O", "EventArgument": "O"}, {"Token": "\u0131n", "EventTrigger": "O", "EventArgument": "O"}, {"Token": "geliri", "EventTrigger": "Gelir-Duyuru", "EventArgument": "O"}, {"Token": "ise", "EventTrigger": "O", "EventArgument": "O"}, {"Token": "7.5", "EventTrigger": "O", "EventArgument": "B-PARA"}, {"Token": "milyon", "EventTrigger": "O", "EventArgument": "I-PARA"}, {"Token": "lirada", "EventTrigger": "O", "EventArgument": "I-PARA"}, {"Token": "kald\u0131", "EventTrigger": "O", "EventArgument": "O"}, {"Token": ".", "EventTrigger": "O", "EventArgument": "O"}]}, {"SentenceId": "25", "SentenceText": "B\u00f6ylelikle ilk yar\u0131da yay\u0131n gelirinin \u00f6nemli bir k\u0131sm\u0131 Anadolu \u2019 da kalm\u0131\u015f oldu .", "Tokens": [{"Token": "B\u00f6ylelikle", "EventTrigger": "O", "EventArgument": "O"}, {"Token": "ilk", "EventTrigger": "O", "EventArgument": "B-ZAMAN"}, {"Token": "yar\u0131da", "EventTrigger": "O", "EventArgument": "I-ZAMAN"}, {"Token": "yay\u0131n", "EventTrigger": "O", "EventArgument": "O"}, {"Token": "gelirinin", "EventTrigger": "Gelir-Duyuru", "EventArgument": "O"}, {"Token": "\u00f6nemli", "EventTrigger": "O", "EventArgument": "O"}, {"Token": "bir", "EventTrigger": "O", "EventArgument": "O"}, {"Token": "k\u0131sm\u0131", "EventTrigger": "O", "EventArgument": "O"}, {"Token": "Anadolu", "EventTrigger": "O", "EventArgument": "O"}, {"Token": "\u2019", "EventTrigger": "O", "EventArgument": "O"}, {"Token": "da", "EventTrigger": "O", "EventArgument": "O"}, {"Token": "kalm\u0131\u015f", "EventTrigger": "O", "EventArgument": "O"}, {"Token": "oldu", "EventTrigger": "O", "EventArgument": "O"}, {"Token": ".", "EventTrigger": "O", "EventArgument": "O"}]}, {"SentenceId": "26", "SentenceText": "Kul\u00fcpler nas\u0131l para kazan\u0131yor Spor Toto S\u00fcper Lig \u2019 de 18 kul\u00fcbe e\u015fit olarak 10.4 milyon lira ayak bast\u0131 paras\u0131 verilecek .", "Tokens": [{"Token": "Kul\u00fcpler", "EventTrigger": "O", "EventArgument": "O"}, {"Token": "nas\u0131l", "EventTrigger": "O", "EventArgument": "O"}, {"Token": "para", "EventTrigger": "O", "EventArgument": "O"}, {"Token": "kazan\u0131yor", "EventTrigger": "O", "EventArgument": "O"}, {"Token": "Spor", "EventTrigger": "O", "EventArgument": "O"}, {"Token": "Toto", "EventTrigger": "O", "EventArgument": "O"}, {"Token": "S\u00fcper", "EventTrigger": "O", "EventArgument": "O"}, {"Token": "Lig", "EventTrigger": "O", "EventArgument": "O"}, {"Token": "\u2019", "EventTrigger": "O", "EventArgument": "O"}, {"Token": "de", "EventTrigger": "O", "EventArgument": "O"}, {"Token": "18", "EventTrigger": "O", "EventArgument": "O"}, {"Token": "kul\u00fcbe", "EventTrigger": "O", "EventArgument": "O"}, {"Token": "e\u015fit", "EventTrigger": "O", "EventArgument": "O"}, {"Token": "olarak", "EventTrigger": "O", "EventArgument": "O"}, {"Token": "10.4", "EventTrigger": "O", "EventArgument": "O"}, {"Token": "milyon", "EventTrigger": "O", "EventArgument": "O"}, {"Token": "lira", "EventTrigger": "O", "EventArgument": "O"}, {"Token": "ayak", "EventTrigger": "O", "EventArgument": "O"}, {"Token": "bast\u0131", "EventTrigger": "O", "EventArgument": "O"}, {"Token": "paras\u0131", "EventTrigger": "O", "EventArgument": "O"}, {"Token": "verilecek", "EventTrigger": "O", "EventArgument": "O"}, {"Token": ".", "EventTrigger": "O", "EventArgument": "O"}]}, {"SentenceId": "27", "SentenceText": "\u015eampiyonluk paras\u0131ndan Fenerbah\u00e7e ve Galatasaray 18 milyon al\u0131yor .", "Tokens": [{"Token": "\u015eampiyonluk", "EventTrigger": "O", "EventArgument": "O"}, {"Token": "paras\u0131ndan", "EventTrigger": "O", "EventArgument": "O"}, {"Token": "Fenerbah\u00e7e", "EventTrigger": "O", "EventArgument": "O"}, {"Token": "ve", "EventTrigger": "O", "EventArgument": "O"}, {"Token": "Galatasaray", "EventTrigger": "O", "EventArgument": "O"}, {"Token": "18", "EventTrigger": "O", "EventArgument": "O"}, {"Token": "milyon", "EventTrigger": "O", "EventArgument": "O"}, {"Token": "al\u0131yor", "EventTrigger": "O", "EventArgument": "O"}, {"Token": ".", "EventTrigger": "O", "EventArgument": "O"}]}, {"SentenceId": "28", "SentenceText": "Be\u015fikta\u015f \u2019 a 14 milyon , Trabzonspor \u2019 a 6.5 milyon ve Bursaspor \u2019 a da 1 milyon veriliyor .", "Tokens": [{"Token": "Be\u015fikta\u015f", "EventTrigger": "O", "EventArgument": "O"}, {"Token": "\u2019", "EventTrigger": "O", "EventArgument": "O"}, {"Token": "a", "EventTrigger": "O", "EventArgument": "O"}, {"Token": "14", "EventTrigger": "O", "EventArgument": "O"}, {"Token": "milyon", "EventTrigger": "O", "EventArgument": "O"}, {"Token": ",", "EventTrigger": "O", "EventArgument": "O"}, {"Token": "Trabzonspor", "EventTrigger": "O", "EventArgument": "O"}, {"Token": "\u2019", "EventTrigger": "O", "EventArgument": "O"}, {"Token": "a", "EventTrigger": "O", "EventArgument": "O"}, {"Token": "6.5", "EventTrigger": "O", "EventArgument": "O"}, {"Token": "milyon", "EventTrigger": "O", "EventArgument": "O"}, {"Token": "ve", "EventTrigger": "O", "EventArgument": "O"}, {"Token": "Bursaspor", "EventTrigger": "O", "EventArgument": "O"}, {"Token": "\u2019", "EventTrigger": "O", "EventArgument": "O"}, {"Token": "a", "EventTrigger": "O", "EventArgument": "O"}, {"Token": "da", "EventTrigger": "O", "EventArgument": "O"}, {"Token": "1", "EventTrigger": "O", "EventArgument": "O"}, {"Token": "milyon", "EventTrigger": "O", "EventArgument": "O"}, {"Token": "veriliyor", "EventTrigger": "O", "EventArgument": "O"}, {"Token": ".", "EventTrigger": "O", "EventArgument": "O"}]}, {"SentenceId": "29", "SentenceText": "Ma\u00e7lardaki galibiyet primi 750 bin TL , beraberlik 375 bin TL olacak .", "Tokens": [{"Token": "Ma\u00e7lardaki", "EventTrigger": "O", "EventArgument": "O"}, {"Token": "galibiyet", "EventTrigger": "O", "EventArgument": "O"}, {"Token": "primi", "EventTrigger": "O", "EventArgument": "O"}, {"Token": "750", "EventTrigger": "O", "EventArgument": "O"}, {"Token": "bin", "EventTrigger": "O", "EventArgument": "O"}, {"Token": "TL", "EventTrigger": "O", "EventArgument": "O"}, {"Token": ",", "EventTrigger": "O", "EventArgument": "O"}, {"Token": "beraberlik", "EventTrigger": "O", "EventArgument": "O"}, {"Token": "375", "EventTrigger": "O", "EventArgument": "O"}, {"Token": "bin", "EventTrigger": "O", "EventArgument": "O"}, {"Token": "TL", "EventTrigger": "O", "EventArgument": "O"}, {"Token": "olacak", "EventTrigger": "O", "EventArgument": "O"}, {"Token": ".", "EventTrigger": "O", "EventArgument": "O"}]}, {"SentenceId": "30", "SentenceText": "Ligi 6 \u2019 nc\u0131 s\u0131rada tamamlayan tak\u0131ma 1.5 milyon lira \u00f6denecek .", "Tokens": [{"Token": "Ligi", "EventTrigger": "O", "EventArgument": "O"}, {"Token": "6", "EventTrigger": "O", "EventArgument": "O"}, {"Token": "\u2019", "EventTrigger": "O", "EventArgument": "O"}, {"Token": "nc\u0131", "EventTrigger": "O", "EventArgument": "O"}, {"Token": "s\u0131rada", "EventTrigger": "O", "EventArgument": "O"}, {"Token": "tamamlayan", "EventTrigger": "O", "EventArgument": "O"}, {"Token": "tak\u0131ma", "EventTrigger": "O", "EventArgument": "O"}, {"Token": "1.5", "EventTrigger": "O", "EventArgument": "O"}, {"Token": "milyon", "EventTrigger": "O", "EventArgument": "O"}, {"Token": "lira", "EventTrigger": "O", "EventArgument": "O"}, {"Token": "\u00f6denecek", "EventTrigger": "O", "EventArgument": "O"}, {"Token": ".", "EventTrigger": "O", "EventArgument": "O"}]}, {"SentenceId": "31", "SentenceText": "5 \u2019 inci olan tak\u0131m 3 milyon lira alacak .", "Tokens": [{"Token": "5", "EventTrigger": "O", "EventArgument": "O"}, {"Token": "\u2019", "EventTrigger": "O", "EventArgument": "O"}, {"Token": "inci", "EventTrigger": "O", "EventArgument": "O"}, {"Token": "olan", "EventTrigger": "O", "EventArgument": "O"}, {"Token": "tak\u0131m", "EventTrigger": "O", "EventArgument": "O"}, {"Token": "3", "EventTrigger": "O", "EventArgument": "O"}, {"Token": "milyon", "EventTrigger": "O", "EventArgument": "O"}, {"Token": "lira", "EventTrigger": "O", "EventArgument": "O"}, {"Token": "alacak", "EventTrigger": "O", "EventArgument": "O"}, {"Token": ".", "EventTrigger": "O", "EventArgument": "O"}]}, {"SentenceId": "32", "SentenceText": "4 \u2019 \u00fcnc\u00fc olan 6 milyon TL , 3 \u2019 \u00fcnc\u00fc olan 9 milyon lira kazanacak .", "Tokens": [{"Token": "4", "EventTrigger": "O", "EventArgument": "O"}, {"Token": "\u2019", "EventTrigger": "O", "EventArgument": "O"}, {"Token": "\u00fcnc\u00fc", "EventTrigger": "O", "EventArgument": "O"}, {"Token": "olan", "EventTrigger": "O", "EventArgument": "O"}, {"Token": "6", "EventTrigger": "O", "EventArgument": "O"}, {"Token": "milyon", "EventTrigger": "O", "EventArgument": "O"}, {"Token": "TL", "EventTrigger": "O", "EventArgument": "O"}, {"Token": ",", "EventTrigger": "O", "EventArgument": "O"}, {"Token": "3", "EventTrigger": "O", "EventArgument": "O"}, {"Token": "\u2019", "EventTrigger": "O", "EventArgument": "O"}, {"Token": "\u00fcnc\u00fc", "EventTrigger": "O", "EventArgument": "O"}, {"Token": "olan", "EventTrigger": "O", "EventArgument": "O"}, {"Token": "9", "EventTrigger": "O", "EventArgument": "O"}, {"Token": "milyon", "EventTrigger": "O", "EventArgument": "O"}, {"Token": "lira", "EventTrigger": "O", "EventArgument": "O"}, {"Token": "kazanacak", "EventTrigger": "O", "EventArgument": "O"}, {"Token": ".", "EventTrigger": "O", "EventArgument": "O"}]}, {"SentenceId": "33", "SentenceText": "2 \u2019 nci olan kul\u00fcp ise 12 milyon liran\u0131n sahibi olacak .", "Tokens": [{"Token": "2", "EventTrigger": "O", "EventArgument": "O"}, {"Token": "\u2019", "EventTrigger": "O", "EventArgument": "O"}, {"Token": "nci", "EventTrigger": "O", "EventArgument": "O"}, {"Token": "olan", "EventTrigger": "O", "EventArgument": "O"}, {"Token": "kul\u00fcp", "EventTrigger": "O", "EventArgument": "O"}, {"Token": "ise", "EventTrigger": "O", "EventArgument": "O"}, {"Token": "12", "EventTrigger": "O", "EventArgument": "O"}, {"Token": "milyon", "EventTrigger": "O", "EventArgument": "O"}, {"Token": "liran\u0131n", "EventTrigger": "O", "EventArgument": "O"}, {"Token": "sahibi", "EventTrigger": "O", "EventArgument": "O"}, {"Token": "olacak", "EventTrigger": "O", "EventArgument": "O"}, {"Token": ".", "EventTrigger": "O", "EventArgument": "O"}]}, {"SentenceId": "34", "SentenceText": "\u015eampiyon olan tak\u0131m ise kupay\u0131 kald\u0131rd\u0131\u011f\u0131 i\u00e7in 15 milyon lira alacak .", "Tokens": [{"Token": "\u015eampiyon", "EventTrigger": "O", "EventArgument": "O"}, {"Token": "olan", "EventTrigger": "O", "EventArgument": "O"}, {"Token": "tak\u0131m", "EventTrigger": "O", "EventArgument": "O"}, {"Token": "ise", "EventTrigger": "O", "EventArgument": "O"}, {"Token": "kupay\u0131", "EventTrigger": "O", "EventArgument": "O"}, {"Token": "kald\u0131rd\u0131\u011f\u0131", "EventTrigger": "O", "EventArgument": "O"}, {"Token": "i\u00e7in", "EventTrigger": "O", "EventArgument": "O"}, {"Token": "15", "EventTrigger": "O", "EventArgument": "O"}, {"Token": "milyon", "EventTrigger": "O", "EventArgument": "O"}, {"Token": "lira", "EventTrigger": "O", "EventArgument": "O"}, {"Token": "alacak", "EventTrigger": "O", "EventArgument": "O"}, {"Token": ".", "EventTrigger": "O", "EventArgument": "O"}]}, {"SentenceId": "35", "SentenceText": "Spor Toto S\u00fcper Lig Avrupa \u2019 da 6 \u2019 nc\u0131 oldu SPOR Toto S\u00fcper Lig futbolcu de\u011ferleri bak\u0131m\u0131ndan Avrupa \u2019 n\u0131n 6 \u2019 nc\u0131 b\u00fcy\u00fck ligi oluyor .", "Tokens": [{"Token": "Spor", "EventTrigger": "O", "EventArgument": "O"}, {"Token": "Toto", "EventTrigger": "O", "EventArgument": "O"}, {"Token": "S\u00fcper", "EventTrigger": "O", "EventArgument": "O"}, {"Token": "Lig", "EventTrigger": "O", "EventArgument": "O"}, {"Token": "Avrupa", "EventTrigger": "O", "EventArgument": "O"}, {"Token": "\u2019", "EventTrigger": "O", "EventArgument": "O"}, {"Token": "da", "EventTrigger": "O", "EventArgument": "O"}, {"Token": "6", "EventTrigger": "O", "EventArgument": "O"}, {"Token": "\u2019", "EventTrigger": "O", "EventArgument": "O"}, {"Token": "nc\u0131", "EventTrigger": "O", "EventArgument": "O"}, {"Token": "oldu", "EventTrigger": "O", "EventArgument": "O"}, {"Token": "SPOR", "EventTrigger": "O", "EventArgument": "O"}, {"Token": "Toto", "EventTrigger": "O", "EventArgument": "O"}, {"Token": "S\u00fcper", "EventTrigger": "O", "EventArgument": "O"}, {"Token": "Lig", "EventTrigger": "O", "EventArgument": "O"}, {"Token": "futbolcu", "EventTrigger": "O", "EventArgument": "O"}, {"Token": "de\u011ferleri", "EventTrigger": "O", "EventArgument": "O"}, {"Token": "bak\u0131m\u0131ndan", "EventTrigger": "O", "EventArgument": "O"}, {"Token": "Avrupa", "EventTrigger": "O", "EventArgument": "O"}, {"Token": "\u2019", "EventTrigger": "O", "EventArgument": "O"}, {"Token": "n\u0131n", "EventTrigger": "O", "EventArgument": "O"}, {"Token": "6", "EventTrigger": "O", "EventArgument": "O"}, {"Token": "\u2019", "EventTrigger": "O", "EventArgument": "O"}, {"Token": "nc\u0131", "EventTrigger": "O", "EventArgument": "O"}, {"Token": "b\u00fcy\u00fck", "EventTrigger": "O", "EventArgument": "O"}, {"Token": "ligi", "EventTrigger": "O", "EventArgument": "O"}, {"Token": "oluyor", "EventTrigger": "O", "EventArgument": "O"}, {"Token": ".", "EventTrigger": "O", "EventArgument": "O"}]}, {"SentenceId": "36", "SentenceText": "784 milyon Euro \u2019 luk futbolcuya sahip S\u00fcper Lig , Hollanda , Portekiz , Yunanistan ve Rusya gibi ligleri geride b\u0131rak\u0131yor .", "Tokens": [{"Token": "784", "EventTrigger": "O", "EventArgument": "O"}, {"Token": "milyon", "EventTrigger": "O", "EventArgument": "O"}, {"Token": "Euro", "EventTrigger": "O", "EventArgument": "O"}, {"Token": "\u2019", "EventTrigger": "O", "EventArgument": "O"}, {"Token": "luk", "EventTrigger": "O", "EventArgument": "O"}, {"Token": "futbolcuya", "EventTrigger": "O", "EventArgument": "O"}, {"Token": "sahip", "EventTrigger": "O", "EventArgument": "O"}, {"Token": "S\u00fcper", "EventTrigger": "O", "EventArgument": "O"}, {"Token": "Lig", "EventTrigger": "O", "EventArgument": "O"}, {"Token": ",", "EventTrigger": "O", "EventArgument": "O"}, {"Token": "Hollanda", "EventTrigger": "O", "EventArgument": "O"}, {"Token": ",", "EventTrigger": "O", "EventArgument": "O"}, {"Token": "Portekiz", "EventTrigger": "O", "EventArgument": "O"}, {"Token": ",", "EventTrigger": "O", "EventArgument": "O"}, {"Token": "Yunanistan", "EventTrigger": "O", "EventArgument": "O"}, {"Token": "ve", "EventTrigger": "O", "EventArgument": "O"}, {"Token": "Rusya", "EventTrigger": "O", "EventArgument": "O"}, {"Token": "gibi", "EventTrigger": "O", "EventArgument": "O"}, {"Token": "ligleri", "EventTrigger": "O", "EventArgument": "O"}, {"Token": "geride", "EventTrigger": "O", "EventArgument": "O"}, {"Token": "b\u0131rak\u0131yor", "EventTrigger": "O", "EventArgument": "O"}, {"Token": ".", "EventTrigger": "O", "EventArgument": "O"}]}, {"SentenceId": "37", "SentenceText": "3.2 milyar Euro \u2019 luk de\u011feriyle \u0130ngiliz Premier Lig ilk s\u0131rada , \u0130spanya ligi 2.5 milyar Euro \u2019 yla 2 \u2019 nci s\u0131rada yer al\u0131yor .", "Tokens": [{"Token": "3.2", "EventTrigger": "O", "EventArgument": "O"}, {"Token": "milyar", "EventTrigger": "O", "EventArgument": "O"}, {"Token": "Euro", "EventTrigger": "O", "EventArgument": "O"}, {"Token": "\u2019", "EventTrigger": "O", "EventArgument": "O"}, {"Token": "luk", "EventTrigger": "O", "EventArgument": "O"}, {"Token": "de\u011feriyle", "EventTrigger": "O", "EventArgument": "O"}, {"Token": "\u0130ngiliz", "EventTrigger": "O", "EventArgument": "O"}, {"Token": "Premier", "EventTrigger": "O", "EventArgument": "O"}, {"Token": "Lig", "EventTrigger": "O", "EventArgument": "O"}, {"Token": "ilk", "EventTrigger": "O", "EventArgument": "O"}, {"Token": "s\u0131rada", "EventTrigger": "O", "EventArgument": "O"}, {"Token": ",", "EventTrigger": "O", "EventArgument": "O"}, {"Token": "\u0130spanya", "EventTrigger": "O", "EventArgument": "O"}, {"Token": "ligi", "EventTrigger": "O", "EventArgument": "O"}, {"Token": "2.5", "EventTrigger": "O", "EventArgument": "O"}, {"Token": "milyar", "EventTrigger": "O", "EventArgument": "O"}, {"Token": "Euro", "EventTrigger": "O", "EventArgument": "O"}, {"Token": "\u2019", "EventTrigger": "O", "EventArgument": "O"}, {"Token": "yla", "EventTrigger": "O", "EventArgument": "O"}, {"Token": "2", "EventTrigger": "O", "EventArgument": "O"}, {"Token": "\u2019", "EventTrigger": "O", "EventArgument": "O"}, {"Token": "nci", "EventTrigger": "O", "EventArgument": "O"}, {"Token": "s\u0131rada", "EventTrigger": "O", "EventArgument": "O"}, {"Token": "yer", "EventTrigger": "O", "EventArgument": "O"}, {"Token": "al\u0131yor", "EventTrigger": "O", "EventArgument": "O"}, {"Token": ".", "EventTrigger": "O", "EventArgument": "O"}]}, {"SentenceId": "38", "SentenceText": "Avrupa \u2019 n\u0131n en de\u011ferli ilk 10 ligi \u015f\u00f6yle s\u0131ralan\u0131yor : Premier Lig 3.2 milyar Euro .", "Tokens": [{"Token": "Avrupa", "EventTrigger": "O", "EventArgument": "O"}, {"Token": "\u2019", "EventTrigger": "O", "EventArgument": "O"}, {"Token": "n\u0131n", "EventTrigger": "O", "EventArgument": "O"}, {"Token": "en", "EventTrigger": "O", "EventArgument": "O"}, {"Token": "de\u011ferli", "EventTrigger": "O", "EventArgument": "O"}, {"Token": "ilk", "EventTrigger": "O", "EventArgument": "O"}, {"Token": "10", "EventTrigger": "O", "EventArgument": "O"}, {"Token": "ligi", "EventTrigger": "O", "EventArgument": "O"}, {"Token": "\u015f\u00f6yle", "EventTrigger": "O", "EventArgument": "O"}, {"Token": "s\u0131ralan\u0131yor", "EventTrigger": "O", "EventArgument": "O"}, {"Token": ":", "EventTrigger": "O", "EventArgument": "O"}, {"Token": "Premier", "EventTrigger": "O", "EventArgument": "O"}, {"Token": "Lig", "EventTrigger": "O", "EventArgument": "O"}, {"Token": "3.2", "EventTrigger": "O", "EventArgument": "O"}, {"Token": "milyar", "EventTrigger": "O", "EventArgument": "O"}, {"Token": "Euro", "EventTrigger": "O", "EventArgument": "O"}, {"Token": ".", "EventTrigger": "O", "EventArgument": "O"}]}, {"SentenceId": "39", "SentenceText": "La Liga 2.5 milyar Euro .", "Tokens": [{"Token": "La", "EventTrigger": "O", "EventArgument": "O"}, {"Token": "Liga", "EventTrigger": "O", "EventArgument": "O"}, {"Token": "2.5", "EventTrigger": "O", "EventArgument": "O"}, {"Token": "milyar", "EventTrigger": "O", "EventArgument": "O"}, {"Token": "Euro", "EventTrigger": "O", "EventArgument": "O"}, {"Token": ".", "EventTrigger": "O", "EventArgument": "O"}]}, {"SentenceId": "40", "SentenceText": "Seri A 2.4 milyar Euro .", "Tokens": [{"Token": "Seri", "EventTrigger": "O", "EventArgument": "O"}, {"Token": "A", "EventTrigger": "O", "EventArgument": "O"}, {"Token": "2.4", "EventTrigger": "O", "EventArgument": "O"}, {"Token": "milyar", "EventTrigger": "O", "EventArgument": "O"}, {"Token": "Euro", "EventTrigger": "O", "EventArgument": "O"}, {"Token": ".", "EventTrigger": "O", "EventArgument": "O"}]}, {"SentenceId": "41", "SentenceText": "Bundesliga 1.7 milyar Euro .", "Tokens": [{"Token": "Bundesliga", "EventTrigger": "O", "EventArgument": "O"}, {"Token": "1.7", "EventTrigger": "O", "EventArgument": "O"}, {"Token": "milyar", "EventTrigger": "O", "EventArgument": "O"}, {"Token": "Euro", "EventTrigger": "O", "EventArgument": "O"}, {"Token": ".", "EventTrigger": "O", "EventArgument": "O"}]}, {"SentenceId": "42", "SentenceText": "Lig 1 1.4 milyar Euro .", "Tokens": [{"Token": "Lig", "EventTrigger": "O", "EventArgument": "O"}, {"Token": "1", "EventTrigger": "O", "EventArgument": "O"}, {"Token": "1.4", "EventTrigger": "O", "EventArgument": "O"}, {"Token": "milyar", "EventTrigger": "O", "EventArgument": "O"}, {"Token": "Euro", "EventTrigger": "O", "EventArgument": "O"}, {"Token": ".", "EventTrigger": "O", "EventArgument": "O"}]}, {"SentenceId": "43", "SentenceText": "S\u00fcper Lig 784 milyon Euro .", "Tokens": [{"Token": "S\u00fcper", "EventTrigger": "O", "EventArgument": "O"}, {"Token": "Lig", "EventTrigger": "O", "EventArgument": "O"}, {"Token": "784", "EventTrigger": "O", "EventArgument": "O"}, {"Token": "milyon", "EventTrigger": "O", "EventArgument": "O"}, {"Token": "Euro", "EventTrigger": "O", "EventArgument": "O"}, {"Token": ".", "EventTrigger": "O", "EventArgument": "O"}]}, {"SentenceId": "44", "SentenceText": "Rusya Ligi 774 milyon Euro .", "Tokens": [{"Token": "Rusya", "EventTrigger": "O", "EventArgument": "O"}, {"Token": "Ligi", "EventTrigger": "O", "EventArgument": "O"}, {"Token": "774", "EventTrigger": "O", "EventArgument": "O"}, {"Token": "milyon", "EventTrigger": "O", "EventArgument": "O"}, {"Token": "Euro", "EventTrigger": "O", "EventArgument": "O"}, {"Token": ".", "EventTrigger": "O", "EventArgument": "O"}]}, {"SentenceId": "45", "SentenceText": "Portekiz Ligi 674 milyon Euro .", "Tokens": [{"Token": "Portekiz", "EventTrigger": "O", "EventArgument": "O"}, {"Token": "Ligi", "EventTrigger": "O", "EventArgument": "O"}, {"Token": "674", "EventTrigger": "O", "EventArgument": "O"}, {"Token": "milyon", "EventTrigger": "O", "EventArgument": "O"}, {"Token": "Euro", "EventTrigger": "O", "EventArgument": "O"}, {"Token": ".", "EventTrigger": "O", "EventArgument": "O"}]}, {"SentenceId": "46", "SentenceText": "Hollanda Ligi 612 milyon Euro .", "Tokens": [{"Token": "Hollanda", "EventTrigger": "O", "EventArgument": "O"}, {"Token": "Ligi", "EventTrigger": "O", "EventArgument": "O"}, {"Token": "612", "EventTrigger": "O", "EventArgument": "O"}, {"Token": "milyon", "EventTrigger": "O", "EventArgument": "O"}, {"Token": "Euro", "EventTrigger": "O", "EventArgument": "O"}, {"Token": ".", "EventTrigger": "O", "EventArgument": "O"}]}, {"SentenceId": "47", "SentenceText": "Yunanistan Ligi 512 milyon Euro .", "Tokens": [{"Token": "Yunanistan", "EventTrigger": "O", "EventArgument": "O"}, {"Token": "Ligi", "EventTrigger": "O", "EventArgument": "O"}, {"Token": "512", "EventTrigger": "O", "EventArgument": "O"}, {"Token": "milyon", "EventTrigger": "O", "EventArgument": "O"}, {"Token": "Euro", "EventTrigger": "O", "EventArgument": "O"}, {"Token": ".", "EventTrigger": "O", "EventArgument": "O"}]}, {"SentenceId": "48", "SentenceText": "H\u00fcrriyet Ceyhun KUBURLU .", "Tokens": [{"Token": "H\u00fcrriyet", "EventTrigger": "O", "EventArgument": "O"}, {"Token": "Ceyhun", "EventTrigger": "O", "EventArgument": "O"}, {"Token": "KUBURLU", "EventTrigger": "O", "EventArgument": "O"}, {"Token": ".", "EventTrigger": "O", "EventArgument": "O"}]}]}