{"DocId": 11688, "Sentences": [{"SentenceId": "1", "SentenceText": "Ar Tar\u0131m G\u00f6zalt\u0131 Pazar\u0131'na al\u0131nd\u0131 .", "Tokens": [{"Token": "Ar", "EventTrigger": "O", "EventArgument": "O"}, {"Token": "Tar\u0131m", "EventTrigger": "O", "EventArgument": "O"}, {"Token": "G\u00f6zalt\u0131", "EventTrigger": "O", "EventArgument": "O"}, {"Token": "Pazar\u0131'na", "EventTrigger": "O", "EventArgument": "O"}, {"Token": "al\u0131nd\u0131", "EventTrigger": "O", "EventArgument": "O"}, {"Token": ".", "EventTrigger": "O", "EventArgument": "O"}]}, {"SentenceId": "2", "SentenceText": "Ar Tar\u0131m hisseleri 29,5 milyon TL varl\u0131\u011f\u0131n borsa d\u0131\u015f\u0131na \u00e7\u0131kar\u0131lmas\u0131 ba\u015fta olmak \u00fczere , bir \u00e7ok nedenle G\u00f6zalt\u0131 Pazar\u0131'na al\u0131nd\u0131 .", "Tokens": [{"Token": "Ar", "EventTrigger": "O", "EventArgument": "B-\u015e\u0130RKET"}, {"Token": "Tar\u0131m", "EventTrigger": "O", "EventArgument": "I-\u015e\u0130RKET"}, {"Token": "hisseleri", "EventTrigger": "O", "EventArgument": "O"}, {"Token": "29,5", "EventTrigger": "O", "EventArgument": "O"}, {"Token": "milyon", "EventTrigger": "O", "EventArgument": "O"}, {"Token": "TL", "EventTrigger": "O", "EventArgument": "O"}, {"Token": "varl\u0131\u011f\u0131n", "EventTrigger": "O", "EventArgument": "O"}, {"Token": "borsa", "EventTrigger": "O", "EventArgument": "O"}, {"Token": "d\u0131\u015f\u0131na", "EventTrigger": "O", "EventArgument": "O"}, {"Token": "\u00e7\u0131kar\u0131lmas\u0131", "EventTrigger": "O", "EventArgument": "O"}, {"Token": "ba\u015fta", "EventTrigger": "O", "EventArgument": "O"}, {"Token": "olmak", "EventTrigger": "O", "EventArgument": "O"}, {"Token": "\u00fczere", "EventTrigger": "O", "EventArgument": "O"}, {"Token": ",", "EventTrigger": "O", "EventArgument": "O"}, {"Token": "bir", "EventTrigger": "O", "EventArgument": "O"}, {"Token": "\u00e7ok", "EventTrigger": "O", "EventArgument": "O"}, {"Token": "nedenle", "EventTrigger": "O", "EventArgument": "O"}, {"Token": "G\u00f6zalt\u0131", "EventTrigger": "O", "EventArgument": "O"}, {"Token": "Pazar\u0131'na", "EventTrigger": "O", "EventArgument": "O"}, {"Token": "al\u0131nd\u0131", "EventTrigger": "O", "EventArgument": "O"}, {"Token": ".", "EventTrigger": "O", "EventArgument": "O"}]}]}